Workbook

Sheet Tariff Database
A1: Parameters: 600 MW DC @ 80% LF = 480 MW avg = 350,400,000 kWh/mo | Peak: 40% (140,160,000 kWh) | Off-Peak: 60% (210,240,000 kWh)
A2: Row | B2: Utility | C2: State | D2: Region | E2: ISO/RTO | F2: Tariff Name | G2: Rate Schedule | H2: Effective Date | I2: Status | J2: Min Load (MW) | K2: Peak Demand ($/kW) | L2: Off-Peak Demand | M2: Energy Peak ($/kWh) | N2: Energy Off-Peak | O2: Fuel/Rider Adj | P2: Contract (Yrs) | Q2: Ratchet % | R2: Demand Ratchet | S2: CIAC | T2: Take-or-Pay | U2: Exit Fee | V2: Credit Req | W2: DC Specific | X2: Collateral | Y2: Blended Rate ($/kWh) | Z2: Annual Cost ($M) | AA2: Protection Score | AB2: Protection Rating | AC2: Rate Components | AD2: Notes
A3: 1 | B3: Public Service Company of Oklahoma (PSO) | C3: OK | D3: Plains | E3: SPP | F3: Large Power & Light (LPL) | G3: Schedule 242/244/246 | H3: 2025-01-30 | I3: Active | J3: 1 | K3: 7.05 | L3: 2.47 | M3: 0.00171 | N3: 0.00125 | O3: 0.035 | P3: 7 | Q3: 90 | R3: Yes | S3: Yes | T3: No | U3: Yes | V3: Yes | W3: No | X3: Yes | Y3: =((K3*600000)+(L3*600000*0.5)+((M3+O3)*140160000)+((N3+O3)*210240000)+500)/350400000 | Z3: =(Y3*350400000*12)/1000000 | AA3: =IF(Q3>=90,3,IF(Q3>=80,2,IF(Q3>=60,1,0)))+IF(P3>=15,3,IF(P3>=10,2,IF(P3>=5,1,0)))+IF(S3="Yes",2,0)+IF(T3="Yes",2,0)+IF(U3="Yes",2,0)+IF(R3="Yes",1,0)+IF(V3="Yes",1,0)+IF(W3="Yes",2,0)+IF(X3="Yes",1,0)+IF(J3>=50,1,0) | AB3: =IF(AA3>=14,"High",IF(AA3>=8,"Mid","Low")) | AC3: Base + Fuel Adj + SPP Trans | AD3: 11 large load customers (779 MW)
A4: 2 | B4: Oklahoma Gas & Electric (OG&E) | C4: OK | D4: Plains | E4: SPP | F4: Power & Light Large | G4: Schedule PL-1 | H4: 2025-01-01 | I4: Active | J4: 1 | K4: 7.08 | L4: 2.5 | M4: 0.007 | N4: 0.005 | O4: 0.038 | P4: 5 | Q4: 0 | R4: No | S4: Yes | T4: No | U4: No | V4: Yes | W4: No | X4: No | Y4: =((K4*600000)+(L4*600000*0.5)+((M4+O4)*140160000)+((N4+O4)*210240000)+500)/350400000 | Z4: =(Y4*350400000*12)/1000000 | AA4: =IF(Q4>=90,3,IF(Q4>=80,2,IF(Q4>=60,1,0)))+IF(P4>=15,3,IF(P4>=10,2,IF(P4>=5,1,0)))+IF(S4="Yes",2,0)+IF(T4="Yes",2,0)+IF(U4="Yes",2,0)+IF(R4="Yes",1,0)+IF(V4="Yes",1,0)+IF(W4="Yes",2,0)+IF(X4="Yes",1,0)+IF(J4>=50,1,0) | AB4: =IF(AA4>=14,"High",IF(AA4>=8,"Mid","Low")) | AC4: Base + Fuel Cost Adj (FCA) | AD4: Large load tariff filing required by July 2026
A5: 3 | B5: SWEPCO (AEP) | C5: TX/LA/AR | D5: Plains | E5: SPP | F5: Large Load Contract | G5: ES-LL Contract | H5: 2025-10-01 | I5: Active | J5: 75 | K5: 8.2 | L5: 3.1 | M5: 0.035 | N5: 0.025 | O5: 0.015 | P5: 12 | Q5: 80 | R5: Yes | S5: Yes | T5: Yes | U5: Yes | V5: Yes | W5: Yes | X5: Yes | Y5: =((K5*600000)+(L5*600000*0.5)+((M5+O5)*140160000)+((N5+O5)*210240000)+500)/350400000 | Z5: =(Y5*350400000*12)/1000000 | AA5: =IF(Q5>=90,3,IF(Q5>=80,2,IF(Q5>=60,1,0)))+IF(P5>=15,3,IF(P5>=10,2,IF(P5>=5,1,0)))+IF(S5="Yes",2,0)+IF(T5="Yes",2,0)+IF(U5="Yes",2,0)+IF(R5="Yes",1,0)+IF(V5="Yes",1,0)+IF(W5="Yes",2,0)+IF(X5="Yes",1,0)+IF(J5>=50,1,0) | AB5: =IF(AA5>=14,"High",IF(AA5>=8,"Mid","Low")) | AC5: All-in Contract Rate | AD5: Large load contract
A6: 4 | B6: ERCOT Market (via REP) | C6: TX | D6: Texas | E6: ERCOT | F6: 4CP Transmission + REP Energy | G6: Market-Based | H6: 2024-01-01 | I6: Active | J6: 1 | K6: 5.5 | L6: 1.5 | M6: 0.045 | N6: 0.028 | O6: 0.015 | P6: 5 | Q6: 0 | R6: No | S6: Yes | T6: No | U6: No | V6: Yes | W6: Yes | X6: Yes | Y6: =((K6*600000)+(L6*600000*0.5)+((M6+O6)*140160000)+((N6+O6)*210240000)+500)/350400000 | Z6: =(Y6*350400000*12)/1000000 | AA6: =IF(Q6>=90,3,IF(Q6>=80,2,IF(Q6>=60,1,0)))+IF(P6>=15,3,IF(P6>=10,2,IF(P6>=5,1,0)))+IF(S6="Yes",2,0)+IF(T6="Yes",2,0)+IF(U6="Yes",2,0)+IF(R6="Yes",1,0)+IF(V6="Yes",1,0)+IF(W6="Yes",2,0)+IF(X6="Yes",1,0)+IF(J6>=50,1,0) | AB6: =IF(AA6>=14,"High",IF(AA6>=8,"Mid","Low")) | AC6: TDU + REP Energy + Ancillary | AD6: Grid operator not retailer; 200+ GW in queue
A7: 5 | B7: Oncor Electric Delivery | C7: TX | D7: Texas | E7: ERCOT | F7: Large Load Delivery + REP | G7: TDU 1700 + REP | H7: 2025-01-01 | I7: Active | J7: 1 | K7: 8.5 | L7: 3.2 | M7: 0.042 | N7: 0.028 | O7: 0.012 | P7: 5 | Q7: 0 | R7: No | S7: Yes | T7: No | U7: No | V7: Yes | W7: No | X7: No | Y7: =((K7*600000)+(L7*600000*0.5)+((M7+O7)*140160000)+((N7+O7)*210240000)+500)/350400000 | Z7: =(Y7*350400000*12)/1000000 | AA7: =IF(Q7>=90,3,IF(Q7>=80,2,IF(Q7>=60,1,0)))+IF(P7>=15,3,IF(P7>=10,2,IF(P7>=5,1,0)))+IF(S7="Yes",2,0)+IF(T7="Yes",2,0)+IF(U7="Yes",2,0)+IF(R7="Yes",1,0)+IF(V7="Yes",1,0)+IF(W7="Yes",2,0)+IF(X7="Yes",1,0)+IF(J7>=50,1,0) | AB7: =IF(AA7>=14,"High",IF(AA7>=8,"Mid","Low")) | AC7: TDU Delivery + REP Energy + Ancillary | AD7: TDU-only + REP energy charges
A8: 6 | B8: CenterPoint Energy Houston | C8: TX | D8: Texas | E8: ERCOT | F8: Large Volume + REP | G8: GSLV-630 + REP | H8: 2025-03-01 | I8: Active | J8: 1 | K8: 8.8 | L8: 3.5 | M8: 0.04 | N8: 0.028 | O8: 0.012 | P8: 5 | Q8: 0 | R8: No | S8: Yes | T8: No | U8: No | V8: Yes | W8: No | X8: No | Y8: =((K8*600000)+(L8*600000*0.5)+((M8+O8)*140160000)+((N8+O8)*210240000)+500)/350400000 | Z8: =(Y8*350400000*12)/1000000 | AA8: =IF(Q8>=90,3,IF(Q8>=80,2,IF(Q8>=60,1,0)))+IF(P8>=15,3,IF(P8>=10,2,IF(P8>=5,1,0)))+IF(S8="Yes",2,0)+IF(T8="Yes",2,0)+IF(U8="Yes",2,0)+IF(R8="Yes",1,0)+IF(V8="Yes",1,0)+IF(W8="Yes",2,0)+IF(X8="Yes",1,0)+IF(J8>=50,1,0) | AB8: =IF(AA8>=14,"High",IF(AA8>=8,"Mid","Low")) | AC8: TDU Delivery + REP Energy + Ancillary | AD8: Houston metro
A9: 7 | B9: CPS Energy (San Antonio) | C9: TX | D9: Texas | E9: ERCOT | F9: Large Commercial Industrial | G9: Rate E LCI | H9: 2025-02-01 | I9: Active | J9: 1 | K9: 9.2 | L9: 3.8 | M9: 0.045 | N9: 0.032 | O9: 0.015 | P9: 5 | Q9: 0 | R9: Yes | S9: Yes | T9: No | U9: No | V9: Yes | W9: No | X9: No | Y9: =((K9*600000)+(L9*600000*0.5)+((M9+O9)*140160000)+((N9+O9)*210240000)+500)/350400000 | Z9: =(Y9*350400000*12)/1000000 | AA9: =IF(Q9>=90,3,IF(Q9>=80,2,IF(Q9>=60,1,0)))+IF(P9>=15,3,IF(P9>=10,2,IF(P9>=5,1,0)))+IF(S9="Yes",2,0)+IF(T9="Yes",2,0)+IF(U9="Yes",2,0)+IF(R9="Yes",1,0)+IF(V9="Yes",1,0)+IF(W9="Yes",2,0)+IF(X9="Yes",1,0)+IF(J9>=50,1,0) | AB9: =IF(AA9>=14,"High",IF(AA9>=8,"Mid","Low")) | AC9: Base + Fuel Adj | AD9: Municipal utility
A10: 8 | B10: Austin Energy | C10: TX | D10: Texas | E10: ERCOT | F10: Large Industrial Service | G10: Rate P4 | H10: 2025-01-01 | I10: Active | J10: 0.3 | K10: 10.5 | L10: 4.2 | M10: 0.055 | N10: 0.038 | O10: 0.012 | P10: 5 | Q10: 0 | R10: Yes | S10: Yes | T10: No | U10: No | V10: Yes | W10: No | X10: No | Y10: =((K10*600000)+(L10*600000*0.5)+((M10+O10)*140160000)+((N10+O10)*210240000)+500)/350400000 | Z10: =(Y10*350400000*12)/1000000 | AA10: =IF(Q10>=90,3,IF(Q10>=80,2,IF(Q10>=60,1,0)))+IF(P10>=15,3,IF(P10>=10,2,IF(P10>=5,1,0)))+IF(S10="Yes",2,0)+IF(T10="Yes",2,0)+IF(U10="Yes",2,0)+IF(R10="Yes",1,0)+IF(V10="Yes",1,0)+IF(W10="Yes",2,0)+IF(X10="Yes",1,0)+IF(J10>=50,1,0) | AB10: =IF(AA10>=14,"High",IF(AA10>=8,"Mid","Low")) | AC10: Base + PSA + Community Benefit | AD10: Municipal; high renewable portfolio
A11: 9 | B11: Georgia Power | C11: GA | D11: Southeast | E11: None | F11: Power and Light Large | G11: Schedule PLL-11 | H11: 2025-01-01 | I11: Active | J11: 0.5 | K11: 9.53 | L11: 4.2 | M11: 0.0143 | N11: 0.0095 | O11: 0.032 | P11: 10 | Q11: 95 | R11: Yes | S11: Yes | T11: Yes | U11: Yes | V11: Yes | W11: No | X11: Yes | Y11: =((K11*600000)+(L11*600000*0.5)+((M11+O11)*140160000)+((N11+O11)*210240000)+500)/350400000 | Z11: =(Y11*350400000*12)/1000000 | AA11: =IF(Q11>=90,3,IF(Q11>=80,2,IF(Q11>=60,1,0)))+IF(P11>=15,3,IF(P11>=10,2,IF(P11>=5,1,0)))+IF(S11="Yes",2,0)+IF(T11="Yes",2,0)+IF(U11="Yes",2,0)+IF(R11="Yes",1,0)+IF(V11="Yes",1,0)+IF(W11="Yes",2,0)+IF(X11="Yes",1,0)+IF(J11>=50,1,0) | AB11: =IF(AA11>=14,"High",IF(AA11>=8,"Mid","Low")) | AC11: Base + ECCR (13.4%) + Fuel Clause | AD11: 51 GW in queue; ECCR adds ~13.4%
A12: 10 | B12: Duke Energy Carolinas | C12: NC | D12: Southeast | E12: None | F12: Large General Service | G12: Schedule LGS | H12: 2024-09-01 | I12: Active | J12: 1 | K12: 5.2 | L12: 3.5 | M12: 0.035 | N12: 0.028 | O12: 0.018 | P12: 5 | Q12: 70 | R12: Yes | S12: Yes | T12: No | U12: No | V12: Yes | W12: No | X12: No | Y12: =((K12*600000)+(L12*600000*0.5)+((M12+O12)*140160000)+((N12+O12)*210240000)+500)/350400000 | Z12: =(Y12*350400000*12)/1000000 | AA12: =IF(Q12>=90,3,IF(Q12>=80,2,IF(Q12>=60,1,0)))+IF(P12>=15,3,IF(P12>=10,2,IF(P12>=5,1,0)))+IF(S12="Yes",2,0)+IF(T12="Yes",2,0)+IF(U12="Yes",2,0)+IF(R12="Yes",1,0)+IF(V12="Yes",1,0)+IF(W12="Yes",2,0)+IF(X12="Yes",1,0)+IF(J12>=50,1,0) | AB12: =IF(AA12>=14,"High",IF(AA12>=8,"Mid","Low")) | AC12: Base + Fuel Rider | AD12: 42 GW in NC queue
A13: 11 | B13: Duke Energy Florida | C13: FL | D13: Southeast | E13: None | F13: Large Load Customer | G13: Schedule LLC-1 (Proposed) | H13: TBD | I13: Suspended / Hearing Pending | J13: 50 | K13: 7.73 | L13: 2.71 | M13: 0.04 | N13: 0.028 | O13: 0.025 | P13: 12 | Q13: 80 | R13: Yes | S13: Yes | T13: Yes | U13: Yes | V13: Yes | W13: Yes | X13: Yes | Y13: =((K13*600000)+(L13*600000*0.5)+((M13+O13)*140160000)+((N13+O13)*210240000)+500)/350400000 | Z13: =(Y13*350400000*12)/1000000 | AA13: =IF(Q13>=90,3,IF(Q13>=80,2,IF(Q13>=60,1,0)))+IF(P13>=15,3,IF(P13>=10,2,IF(P13>=5,1,0)))+IF(S13="Yes",2,0)+IF(T13="Yes",2,0)+IF(U13="Yes",2,0)+IF(R13="Yes",1,0)+IF(V13="Yes",1,0)+IF(W13="Yes",2,0)+IF(X13="Yes",1,0)+IF(J13>=50,1,0) | AB13: =IF(AA13>=14,"High",IF(AA13>=8,"Mid","Low")) | AC13: Base + Fuel Clause (Incremental) | AD13: SUSPENDED: Docket 20250113-EI suspended Oct 2025. Final hearing scheduled April 2026. Rates are HYPOTHETICAL until approval.
A14: 12 | B14: Florida Power & Light (FPL) | C14: FL | D14: Southeast | E14: None | F14: Large Load Contract Service | G14: Schedule LLCS-1 (Approved) | H14: 2026-01-01 | I14: Active | J14: 50 | K14: 35.08 | L14: 14.04 | M14: 0.085 | N14: 0.055 | O14: 0.015 | P14: 20 | Q14: 90 | R14: Yes | S14: Yes | T14: Yes | U14: Yes | V14: Yes | W14: Yes | X14: Yes | Y14: =((K14*600000)+(L14*600000*0.5)+((M14+O14)*140160000)+((N14+O14)*210240000)+500)/350400000 | Z14: =(Y14*350400000*12)/1000000 | AA14: =IF(Q14>=90,3,IF(Q14>=80,2,IF(Q14>=60,1,0)))+IF(P14>=15,3,IF(P14>=10,2,IF(P14>=5,1,0)))+IF(S14="Yes",2,0)+IF(T14="Yes",2,0)+IF(U14="Yes",2,0)+IF(R14="Yes",1,0)+IF(V14="Yes",1,0)+IF(W14="Yes",2,0)+IF(X14="Yes",1,0)+IF(J14>=50,1,0) | AB14: =IF(AA14>=14,"High",IF(AA14>=8,"Mid","Low")) | AC14: Incremental Generation + Fuel | AD14: APPROVED: Includes Incremental Generation Charge (IGC) $28.07/kW + Base $7.01/kW. Marginal cost tariff - highest Southeast rate.
... A74: 72 | B74: National Grid (RI) | C74: RI | D74: Northeast | E74: ISO-NE | F74: Large Demand | G74: Rate G-32 | H74: 2025-01-01 | I74: Active | J74: 0.2 | K74: 13.5 | L74: 5.8 | M74: 0.108 | N74: 0.075 | O74: 0.02 | P74: 5 | Q74: 0 | R74: Yes | S74: Yes | T74: No | U74: No | V74: Yes | W74: No | X74: No | Y74: =((K74*600000)+(L74*600000*0.5)+((M74+O74)*140160000)+((N74+O74)*210240000)+500)/350400000 | Z74: =(Y74*350400000*12)/1000000 | AA74: =IF(Q74>=90,3,IF(Q74>=80,2,IF(Q74>=60,1,0)))+IF(P74>=15,3,IF(P74>=10,2,IF(P74>=5,1,0)))+IF(S74="Yes",2,0)+IF(T74="Yes",2,0)+IF(U74="Yes",2,0)+IF(R74="Yes",1,0)+IF(V74="Yes",1,0)+IF(W74="Yes",2,0)+IF(X74="Yes",1,0)+IF(J74>=50,1,0) | AB74: =IF(AA74>=14,"High",IF(AA74>=8,"Mid","Low")) | AC74: Base + Trans + Dist | AD74: Rhode Island service territory
A75: 73 | B75: AEP Appalachian Power | C75: VA/WV | D75: Southeast | E75: PJM | F75: Large General Service | G75: Schedule LGS | H75: 2025-01-30 | I75: Active | J75: 1 | K75: 13.5 | L75: 6.75 | M75: 0.0285 | N75: 0.0215 | O75: 0.028 | P75: 5 | Q75: 80 | R75: Yes | S75: Yes | T75: No | U75: Yes | V75: Yes | W75: No | X75: No | Y75: =((K75*600000)+(L75*600000*0.5)+((M75+O75)*140160000)+((N75+O75)*210240000)+500)/350400000 | Z75: =(Y75*350400000*12)/1000000 | AA75: =IF(Q75>=90,3,IF(Q75>=80,2,IF(Q75>=60,1,0)))+IF(P75>=15,3,IF(P75>=10,2,IF(P75>=5,1,0)))+IF(S75="Yes",2,0)+IF(T75="Yes",2,0)+IF(U75="Yes",2,0)+IF(R75="Yes",1,0)+IF(V75="Yes",1,0)+IF(W75="Yes",2,0)+IF(X75="Yes",1,0)+IF(J75>=50,1,0) | AB75: =IF(AA75>=14,"High",IF(AA75>=8,"Mid","Low")) | AC75: Base + Fuel Adj + Trans
A76: 74 | B76: AEP Indiana Michigan Power | C76: IN/MI | D76: Midwest | E76: PJM/MISO | F76: Large Power Service | G76: Schedule LPS | H76: 2025-01-30 | I76: Active | J76: 1 | K76: 12.8 | L76: 6.4 | M76: 0.0265 | N76: 0.0198 | O76: 0.025 | P76: 5 | Q76: 75 | R76: Yes | S76: No | T76: No | U76: No | V76: Yes | W76: No | X76: No | Y76: =((K76*600000)+(L76*600000*0.5)+((M76+O76)*140160000)+((N76+O76)*210240000)+500)/350400000 | Z76: =(Y76*350400000*12)/1000000 | AA76: =IF(Q76>=90,3,IF(Q76>=80,2,IF(Q76>=60,1,0)))+IF(P76>=15,3,IF(P76>=10,2,IF(P76>=5,1,0)))+IF(S76="Yes",2,0)+IF(T76="Yes",2,0)+IF(U76="Yes",2,0)+IF(R76="Yes",1,0)+IF(V76="Yes",1,0)+IF(W76="Yes",2,0)+IF(X76="Yes",1,0)+IF(J76>=50,1,0) | AB76: =IF(AA76>=14,"High",IF(AA76>=8,"Mid","Low")) | AC76: Base + Fuel Adj + Trans
A77: 75 | B77: AEP Kentucky Power | C77: KY | D77: Southeast | E77: PJM | F77: Large General Service | G77: Schedule LGS | H77: 2025-01-30 | I77: Active | J77: 1 | K77: 11.95 | L77: 5.98 | M77: 0.0258 | N77: 0.0195 | O77: 0.03 | P77: 5 | Q77: 80 | R77: Yes | S77: Yes | T77: No | U77: Yes | V77: Yes | W77: No | X77: No | Y77: =((K77*600000)+(L77*600000*0.5)+((M77+O77)*140160000)+((N77+O77)*210240000)+500)/350400000 | Z77: =(Y77*350400000*12)/1000000 | AA77: =IF(Q77>=90,3,IF(Q77>=80,2,IF(Q77>=60,1,0)))+IF(P77>=15,3,IF(P77>=10,2,IF(P77>=5,1,0)))+IF(S77="Yes",2,0)+IF(T77="Yes",2,0)+IF(U77="Yes",2,0)+IF(R77="Yes",1,0)+IF(V77="Yes",1,0)+IF(W77="Yes",2,0)+IF(X77="Yes",1,0)+IF(J77>=50,1,0) | AB77: =IF(AA77>=14,"High",IF(AA77>=8,"Mid","Low")) | AC77: Base + Fuel Adj + Trans
A78: 76 | B78: Entergy Arkansas | C78: AR | D78: South Central | E78: MISO | F78: Large General Service | G78: Schedule LGS-TOD | H78: 2025-01-30 | I78: Active | J78: 1 | K78: 9.85 | L78: 4.93 | M78: 0.0235 | N78: 0.0175 | O78: 0.022 | P78: 5 | Q78: 70 | R78: Yes | S78: No | T78: No | U78: No | V78: Yes | W78: No | X78: No | Y78: =((K78*600000)+(L78*600000*0.5)+((M78+O78)*140160000)+((N78+O78)*210240000)+500)/350400000 | Z78: =(Y78*350400000*12)/1000000 | AA78: =IF(Q78>=90,3,IF(Q78>=80,2,IF(Q78>=60,1,0)))+IF(P78>=15,3,IF(P78>=10,2,IF(P78>=5,1,0)))+IF(S78="Yes",2,0)+IF(T78="Yes",2,0)+IF(U78="Yes",2,0)+IF(R78="Yes",1,0)+IF(V78="Yes",1,0)+IF(W78="Yes",2,0)+IF(X78="Yes",1,0)+IF(J78>=50,1,0) | AB78: =IF(AA78>=14,"High",IF(AA78>=8,"Mid","Low")) | AC78: Base + Fuel Adj + Trans
A79: 77 | B79: Entergy Texas | C79: TX | D79: Gulf Coast | E79: MISO | F79: Large Industrial Power | G79: Schedule LIP | H79: 2025-01-30 | I79: Active | J79: 1 | K79: 10.25 | L79: 5.13 | M79: 0.0248 | N79: 0.0185 | O79: 0.024 | P79: 5 | Q79: 75 | R79: Yes | S79: No | T79: No | U79: No | V79: Yes | W79: No | X79: No | Y79: =((K79*600000)+(L79*600000*0.5)+((M79+O79)*140160000)+((N79+O79)*210240000)+500)/350400000 | Z79: =(Y79*350400000*12)/1000000 | AA79: =IF(Q79>=90,3,IF(Q79>=80,2,IF(Q79>=60,1,0)))+IF(P79>=15,3,IF(P79>=10,2,IF(P79>=5,1,0)))+IF(S79="Yes",2,0)+IF(T79="Yes",2,0)+IF(U79="Yes",2,0)+IF(R79="Yes",1,0)+IF(V79="Yes",1,0)+IF(W79="Yes",2,0)+IF(X79="Yes",1,0)+IF(J79>=50,1,0) | AB79: =IF(AA79>=14,"High",IF(AA79>=8,"Mid","Low")) | AC79: Base + Fuel Adj + Trans
A80: 78 | B80: Entergy Mississippi | C80: MS | D80: Southeast | E80: MISO | F80: Large General Service | G80: Schedule LGS | H80: 2025-01-30 | I80: Active | J80: 1 | K80: 9.65 | L80: 4.83 | M80: 0.0228 | N80: 0.0172 | O80: 0.023 | P80: 5 | Q80: 70 | R80: Yes | S80: No | T80: No | U80: No | V80: Yes | W80: No | X80: No | Y80: =((K80*600000)+(L80*600000*0.5)+((M80+O80)*140160000)+((N80+O80)*210240000)+500)/350400000 | Z80: =(Y80*350400000*12)/1000000 | AA80: =IF(Q80>=90,3,IF(Q80>=80,2,IF(Q80>=60,1,0)))+IF(P80>=15,3,IF(P80>=10,2,IF(P80>=5,1,0)))+IF(S80="Yes",2,0)+IF(T80="Yes",2,0)+IF(U80="Yes",2,0)+IF(R80="Yes",1,0)+IF(V80="Yes",1,0)+IF(W80="Yes",2,0)+IF(X80="Yes",1,0)+IF(J80>=50,1,0) | AB80: =IF(AA80>=14,"High",IF(AA80>=8,"Mid","Low")) | AC80: Base + Fuel Adj + Trans
A81: 79 | B81: Entergy New Orleans | C81: LA | D81: Gulf Coast | E81: MISO | F81: Large Electric Service | G81: Schedule LES | H81: 2025-01-30 | I81: Active | J81: 0.5 | K81: 11.45 | L81: 5.73 | M81: 0.0265 | N81: 0.0198 | O81: 0.026 | P81: 5 | Q81: 75 | R81: Yes | S81: No | T81: No | U81: No | V81: Yes | W81: No | X81: No | Y81: =((K81*600000)+(L81*600000*0.5)+((M81+O81)*140160000)+((N81+O81)*210240000)+500)/350400000 | Z81: =(Y81*350400000*12)/1000000 | AA81: =IF(Q81>=90,3,IF(Q81>=80,2,IF(Q81>=60,1,0)))+IF(P81>=15,3,IF(P81>=10,2,IF(P81>=5,1,0)))+IF(S81="Yes",2,0)+IF(T81="Yes",2,0)+IF(U81="Yes",2,0)+IF(R81="Yes",1,0)+IF(V81="Yes",1,0)+IF(W81="Yes",2,0)+IF(X81="Yes",1,0)+IF(J81>=50,1,0) | AB81: =IF(AA81>=14,"High",IF(AA81>=8,"Mid","Low")) | AC81: Base + Fuel Adj + Trans
A82: 80 | B82: Empire District Electric | C82: MO/KS/AR/OK | D82: Plains | E82: SPP | F82: Large Power Service | G82: Schedule LP | H82: 2025-01-30 | I82: Active | J82: 1 | K82: 10.85 | L82: 5.43 | M82: 0.0255 | N82: 0.0192 | O82: 0.028 | P82: 5 | Q82: 75 | R82: Yes | S82: No | T82: No | U82: No | V82: Yes | W82: No | X82: No | Y82: =((K82*600000)+(L82*600000*0.5)+((M82+O82)*140160000)+((N82+O82)*210240000)+500)/350400000 | Z82: =(Y82*350400000*12)/1000000 | AA82: =IF(Q82>=90,3,IF(Q82>=80,2,IF(Q82>=60,1,0)))+IF(P82>=15,3,IF(P82>=10,2,IF(P82>=5,1,0)))+IF(S82="Yes",2,0)+IF(T82="Yes",2,0)+IF(U82="Yes",2,0)+IF(R82="Yes",1,0)+IF(V82="Yes",1,0)+IF(W82="Yes",2,0)+IF(X82="Yes",1,0)+IF(J82>=50,1,0) | AB82: =IF(AA82>=14,"High",IF(AA82>=8,"Mid","Low")) | AC82: Base + Fuel Adj + Trans
A83: 81 | B83: Southwestern Public Service (Xcel) | C83: TX/NM | D83: Southwest | E83: SPP | F83: Large General Service | G83: Schedule 36 | H83: 2025-01-30 | I83: Active | J83: 1 | K83: 11.25 | L83: 5.63 | M83: 0.0268 | N83: 0.0202 | O83: 0.025 | P83: 5 | Q83: 80 | R83: Yes | S83: No | T83: No | U83: No | V83: Yes | W83: No | X83: No | Y83: =((K83*600000)+(L83*600000*0.5)+((M83+O83)*140160000)+((N83+O83)*210240000)+500)/350400000 | Z83: =(Y83*350400000*12)/1000000 | AA83: =IF(Q83>=90,3,IF(Q83>=80,2,IF(Q83>=60,1,0)))+IF(P83>=15,3,IF(P83>=10,2,IF(P83>=5,1,0)))+IF(S83="Yes",2,0)+IF(T83="Yes",2,0)+IF(U83="Yes",2,0)+IF(R83="Yes",1,0)+IF(V83="Yes",1,0)+IF(W83="Yes",2,0)+IF(X83="Yes",1,0)+IF(J83>=50,1,0) | AB83: =IF(AA83>=14,"High",IF(AA83>=8,"Mid","Low")) | AC83: Base + Fuel Adj + Trans
A84: 82 | B84: Public Service Company of New Mexico (PNM) | C84: NM | D84: Southwest | E84: None (EIM) | F84: Large Power Service | G84: Schedule 3B | H84: 2025-01-30 | I84: Active | J84: 1 | K84: 12.45 | L84: 6.23 | M84: 0.0285 | N84: 0.0215 | O84: 0.018 | P84: 5 | Q84: 75 | R84: Yes | S84: No | T84: No | U84: No | V84: Yes | W84: No | X84: No | Y84: =((K84*600000)+(L84*600000*0.5)+((M84+O84)*140160000)+((N84+O84)*210240000)+500)/350400000 | Z84: =(Y84*350400000*12)/1000000 | AA84: =IF(Q84>=90,3,IF(Q84>=80,2,IF(Q84>=60,1,0)))+IF(P84>=15,3,IF(P84>=10,2,IF(P84>=5,1,0)))+IF(S84="Yes",2,0)+IF(T84="Yes",2,0)+IF(U84="Yes",2,0)+IF(R84="Yes",1,0)+IF(V84="Yes",1,0)+IF(W84="Yes",2,0)+IF(X84="Yes",1,0)+IF(J84>=50,1,0) | AB84: =IF(AA84>=14,"High",IF(AA84>=8,"Mid","Low")) | AC84: Base + Fuel Adj + Trans
A85: 83 | B85: NorthWestern Energy (MT) | C85: MT | D85: Northwest | E85: None | F85: Large General Service | G85: Schedule LGS | H85: 2025-01-30 | I85: Active | J85: 1 | K85: 10.95 | L85: 5.48 | M85: 0.0248 | N85: 0.0188 | O85: 0.02 | P85: 5 | Q85: 70 | R85: Yes | S85: No | T85: No | U85: No | V85: Yes | W85: No | X85: No | Y85: =((K85*600000)+(L85*600000*0.5)+((M85+O85)*140160000)+((N85+O85)*210240000)+500)/350400000 | Z85: =(Y85*350400000*12)/1000000 | AA85: =IF(Q85>=90,3,IF(Q85>=80,2,IF(Q85>=60,1,0)))+IF(P85>=15,3,IF(P85>=10,2,IF(P85>=5,1,0)))+IF(S85="Yes",2,0)+IF(T85="Yes",2,0)+IF(U85="Yes",2,0)+IF(R85="Yes",1,0)+IF(V85="Yes",1,0)+IF(W85="Yes",2,0)+IF(X85="Yes",1,0)+IF(J85>=50,1,0) | AB85: =IF(AA85>=14,"High",IF(AA85>=8,"Mid","Low")) | AC85: Base + Fuel Adj + Trans
A86: 84 | B86: NorthWestern Energy (SD) | C86: SD | D86: Plains | E86: None | F86: Large General Service | G86: Schedule LGS | H86: 2025-01-30 | I86: Active | J86: 1 | K86: 10.75 | L86: 5.38 | M86: 0.0242 | N86: 0.0182 | O86: 0.019 | P86: 5 | Q86: 70 | R86: Yes | S86: No | T86: No | U86: No | V86: Yes | W86: No | X86: No | Y86: =((K86*600000)+(L86*600000*0.5)+((M86+O86)*140160000)+((N86+O86)*210240000)+500)/350400000 | Z86: =(Y86*350400000*12)/1000000 | AA86: =IF(Q86>=90,3,IF(Q86>=80,2,IF(Q86>=60,1,0)))+IF(P86>=15,3,IF(P86>=10,2,IF(P86>=5,1,0)))+IF(S86="Yes",2,0)+IF(T86="Yes",2,0)+IF(U86="Yes",2,0)+IF(R86="Yes",1,0)+IF(V86="Yes",1,0)+IF(W86="Yes",2,0)+IF(X86="Yes",1,0)+IF(J86>=50,1,0) | AB86: =IF(AA86>=14,"High",IF(AA86>=8,"Mid","Low")) | AC86: Base + Fuel Adj + Trans
... A90: 88 | B90: Duke Energy Ohio | C90: OH | D90: Midwest | E90: PJM | F90: Rate DP | G90: Schedule DP | H90: 2025-01-30 | I90: Active | J90: 1 | K90: 11.85 | L90: 5.93 | M90: 0.0262 | N90: 0.0198 | O90: 0.024 | P90: 5 | Q90: 80 | R90: Yes | S90: No | T90: No | U90: No | V90: Yes | W90: No | X90: No | Y90: =((K90*600000)+(L90*600000*0.5)+((M90+O90)*140160000)+((N90+O90)*210240000)+500)/350400000 | Z90: =(Y90*350400000*12)/1000000 | AA90: =IF(Q90>=90,3,IF(Q90>=80,2,IF(Q90>=60,1,0)))+IF(P90>=15,3,IF(P90>=10,2,IF(P90>=5,1,0)))+IF(S90="Yes",2,0)+IF(T90="Yes",2,0)+IF(U90="Yes",2,0)+IF(R90="Yes",1,0)+IF(V90="Yes",1,0)+IF(W90="Yes",2,0)+IF(X90="Yes",1,0)+IF(J90>=50,1,0) | AB90: =IF(AA90>=14,"High",IF(AA90>=8,"Mid","Low")) | AC90: Base + Fuel Adj + Trans

Sheet Blended Rate Analysis
A1: Rank | B1: Utility | C1: State | D1: Region | E1: ISO/RTO | F1: Peak Demand ($/kW) | G1: Off-Peak Demand | H1: Energy Peak | I1: Energy Off-Peak | J1: Fuel Adj | K1: Blended Rate ($/kWh) | L1: Annual Cost ($M) | M1: Protection Rating | N1: Status
A2: 1 | B2: ='Tariff Database'!B18 | C2: ='Tariff Database'!C18 | D2: ='Tariff Database'!D18 | E2: ='Tariff Database'!E18 | F2: ='Tariff Database'!K18 | G2: ='Tariff Database'!L18 | H2: ='Tariff Database'!M18 | I2: ='Tariff Database'!N18 | J2: ='Tariff Database'!O18 | K2: ='Tariff Database'!Y18 | L2: ='Tariff Database'!Z18 | M2: ='Tariff Database'!AB18 | N2: ='Tariff Database'!I18
A3: 2 | B3: ='Tariff Database'!B3 | C3: ='Tariff Database'!C3 | D3: ='Tariff Database'!D3 | E3: ='Tariff Database'!E3 | F3: ='Tariff Database'!K3 | G3: ='Tariff Database'!L3 | H3: ='Tariff Database'!M3 | I3: ='Tariff Database'!N3 | J3: ='Tariff Database'!O3 | K3: ='Tariff Database'!Y3 | L3: ='Tariff Database'!Z3 | M3: ='Tariff Database'!AB3 | N3: ='Tariff Database'!I3
A4: 3 | B4: ='Tariff Database'!B48 | C4: ='Tariff Database'!C48 | D4: ='Tariff Database'!D48 | E4: ='Tariff Database'!E48 | F4: ='Tariff Database'!K48 | G4: ='Tariff Database'!L48 | H4: ='Tariff Database'!M48 | I4: ='Tariff Database'!N48 | J4: ='Tariff Database'!O48 | K4: ='Tariff Database'!Y48 | L4: ='Tariff Database'!Z48 | M4: ='Tariff Database'!AB48 | N4: ='Tariff Database'!I48
A5: 4 | B5: ='Tariff Database'!B23 | C5: ='Tariff Database'!C23 | D5: ='Tariff Database'!D23 | E5: ='Tariff Database'!E23 | F5: ='Tariff Database'!K23 | G5: ='Tariff Database'!L23 | H5: ='Tariff Database'!M23 | I5: ='Tariff Database'!N23 | J5: ='Tariff Database'!O23 | K5: ='Tariff Database'!Y23 | L5: ='Tariff Database'!Z23 | M5: ='Tariff Database'!AB23 | N5: ='Tariff Database'!I23
A6: 5 | B6: ='Tariff Database'!B49 | C6: ='Tariff Database'!C49 | D6: ='Tariff Database'!D49 | E6: ='Tariff Database'!E49 | F6: ='Tariff Database'!K49 | G6: ='Tariff Database'!L49 | H6: ='Tariff Database'!M49 | I6: ='Tariff Database'!N49 | J6: ='Tariff Database'!O49 | K6: ='Tariff Database'!Y49 | L6: ='Tariff Database'!Z49 | M6: ='Tariff Database'!AB49 | N6: ='Tariff Database'!I49
A7: 6 | B7: ='Tariff Database'!B45 | C7: ='Tariff Database'!C45 | D7: ='Tariff Database'!D45 | E7: ='Tariff Database'!E45 | F7: ='Tariff Database'!K45 | G7: ='Tariff Database'!L45 | H7: ='Tariff Database'!M45 | I7: ='Tariff Database'!N45 | J7: ='Tariff Database'!O45 | K7: ='Tariff Database'!Y45 | L7: ='Tariff Database'!Z45 | M7: ='Tariff Database'!AB45 | N7: ='Tariff Database'!I45
A8: 7 | B8: ='Tariff Database'!B4 | C8: ='Tariff Database'!C4 | D8: ='Tariff Database'!D4 | E8: ='Tariff Database'!E4 | F8: ='Tariff Database'!K4 | G8: ='Tariff Database'!L4 | H8: ='Tariff Database'!M4 | I8: ='Tariff Database'!N4 | J8: ='Tariff Database'!O4 | K8: ='Tariff Database'!Y4 | L8: ='Tariff Database'!Z4 | M8: ='Tariff Database'!AB4 | N8: ='Tariff Database'!I4
A9: 8 | B9: ='Tariff Database'!B51 | C9: ='Tariff Database'!C51 | D9: ='Tariff Database'!D51 | E9: ='Tariff Database'!E51 | F9: ='Tariff Database'!K51 | G9: ='Tariff Database'!L51 | H9: ='Tariff Database'!M51 | I9: ='Tariff Database'!N51 | J9: ='Tariff Database'!O51 | K9: ='Tariff Database'!Y51 | L9: ='Tariff Database'!Z51 | M9: ='Tariff Database'!AB51 | N9: ='Tariff Database'!I51
A10: 9 | B10: ='Tariff Database'!B40 | C10: ='Tariff Database'!C40 | D10: ='Tariff Database'!D40 | E10: ='Tariff Database'!E40 | F10: ='Tariff Database'!K40 | G10: ='Tariff Database'!L40 | H10: ='Tariff Database'!M40 | I10: ='Tariff Database'!N40 | J10: ='Tariff Database'!O40 | K10: ='Tariff Database'!Y40 | L10: ='Tariff Database'!Z40 | M10: ='Tariff Database'!AB40 | N10: ='Tariff Database'!I40
A11: 10 | B11: ='Tariff Database'!B50 | C11: ='Tariff Database'!C50 | D11: ='Tariff Database'!D50 | E11: ='Tariff Database'!E50 | F11: ='Tariff Database'!K50 | G11: ='Tariff Database'!L50 | H11: ='Tariff Database'!M50 | I11: ='Tariff Database'!N50 | J11: ='Tariff Database'!O50 | K11: ='Tariff Database'!Y50 | L11: ='Tariff Database'!Z50 | M11: ='Tariff Database'!AB50 | N11: ='Tariff Database'!I50
A12: 11 | B12: ='Tariff Database'!B6 | C12: ='Tariff Database'!C6 | D12: ='Tariff Database'!D6 | E12: ='Tariff Database'!E6 | F12: ='Tariff Database'!K6 | G12: ='Tariff Database'!L6 | H12: ='Tariff Database'!M6 | I12: ='Tariff Database'!N6 | J12: ='Tariff Database'!O6 | K12: ='Tariff Database'!Y6 | L12: ='Tariff Database'!Z6 | M12: ='Tariff Database'!AB6 | N12: ='Tariff Database'!I6
A13: 12 | B13: ='Tariff Database'!B5 | C13: ='Tariff Database'!C5 | D13: ='Tariff Database'!D5 | E13: ='Tariff Database'!E5 | F13: ='Tariff Database'!K5 | G13: ='Tariff Database'!L5 | H13: ='Tariff Database'!M5 | I13: ='Tariff Database'!N5 | J13: ='Tariff Database'!O5 | K13: ='Tariff Database'!Y5 | L13: ='Tariff Database'!Z5 | M13: ='Tariff Database'!AB5 | N13: ='Tariff Database'!I5
A14: 13 | B14: ='Tariff Database'!B12 | C14: ='Tariff Database'!C12 | D14: ='Tariff Database'!D12 | E14: ='Tariff Database'!E12 | F14: ='Tariff Database'!K12 | G14: ='Tariff Database'!L12 | H14: ='Tariff Database'!M12 | I14: ='Tariff Database'!N12 | J14: ='Tariff Database'!O12 | K14: ='Tariff Database'!Y12 | L14: ='Tariff Database'!Z12 | M14: ='Tariff Database'!AB12 | N14: ='Tariff Database'!I12
A15: 14 | B15: ='Tariff Database'!B38 | C15: ='Tariff Database'!C38 | D15: ='Tariff Database'!D38 | E15: ='Tariff Database'!E38 | F15: ='Tariff Database'!K38 | G15: ='Tariff Database'!L38 | H15: ='Tariff Database'!M38 | I15: ='Tariff Database'!N38 | J15: ='Tariff Database'!O38 | K15: ='Tariff Database'!Y38 | L15: ='Tariff Database'!Z38 | M15: ='Tariff Database'!AB38 | N15: ='Tariff Database'!I38
A16: 15 | B16: ='Tariff Database'!B8 | C16: ='Tariff Database'!C8 | D16: ='Tariff Database'!D8 | E16: ='Tariff Database'!E8 | F16: ='Tariff Database'!K8 | G16: ='Tariff Database'!L8 | H16: ='Tariff Database'!M8 | I16: ='Tariff Database'!N8 | J16: ='Tariff Database'!O8 | K16: ='Tariff Database'!Y8 | L16: ='Tariff Database'!Z8 | M16: ='Tariff Database'!AB8 | N16: ='Tariff Database'!I8
A17: 16 | B17: ='Tariff Database'!B7 | C17: ='Tariff Database'!C7 | D17: ='Tariff Database'!D7 | E17: ='Tariff Database'!E7 | F17: ='Tariff Database'!K7 | G17: ='Tariff Database'!L7 | H17: ='Tariff Database'!M7 | I17: ='Tariff Database'!N7 | J17: ='Tariff Database'!O7 | K17: ='Tariff Database'!Y7 | L17: ='Tariff Database'!Z7 | M17: ='Tariff Database'!AB7 | N17: ='Tariff Database'!I7
A18: 17 | B18: ='Tariff Database'!B11 | C18: ='Tariff Database'!C11 | D18: ='Tariff Database'!D11 | E18: ='Tariff Database'!E11 | F18: ='Tariff Database'!K11 | G18: ='Tariff Database'!L11 | H18: ='Tariff Database'!M11 | I18: ='Tariff Database'!N11 | J18: ='Tariff Database'!O11 | K18: ='Tariff Database'!Y11 | L18: ='Tariff Database'!Z11 | M18: ='Tariff Database'!AB11 | N18: ='Tariff Database'!I11
A19: 18 | B19: ='Tariff Database'!B37 | C19: ='Tariff Database'!C37 | D19: ='Tariff Database'!D37 | E19: ='Tariff Database'!E37 | F19: ='Tariff Database'!K37 | G19: ='Tariff Database'!L37 | H19: ='Tariff Database'!M37 | I19: ='Tariff Database'!N37 | J19: ='Tariff Database'!O37 | K19: ='Tariff Database'!Y37 | L19: ='Tariff Database'!Z37 | M19: ='Tariff Database'!AB37 | N19: ='Tariff Database'!I37
A20: 19 | B20: ='Tariff Database'!B47 | C20: ='Tariff Database'!C47 | D20: ='Tariff Database'!D47 | E20: ='Tariff Database'!E47 | F20: ='Tariff Database'!K47 | G20: ='Tariff Database'!L47 | H20: ='Tariff Database'!M47 | I20: ='Tariff Database'!N47 | J20: ='Tariff Database'!O47 | K20: ='Tariff Database'!Y47 | L20: ='Tariff Database'!Z47 | M20: ='Tariff Database'!AB47 | N20: ='Tariff Database'!I47
A21: 20 | B21: ='Tariff Database'!B22 | C21: ='Tariff Database'!C22 | D21: ='Tariff Database'!D22 | E21: ='Tariff Database'!E22 | F21: ='Tariff Database'!K22 | G21: ='Tariff Database'!L22 | H21: ='Tariff Database'!M22 | I21: ='Tariff Database'!N22 | J21: ='Tariff Database'!O22 | K21: ='Tariff Database'!Y22 | L21: ='Tariff Database'!Z22 | M21: ='Tariff Database'!AB22 | N21: ='Tariff Database'!I22
A22: 21 | B22: ='Tariff Database'!B25 | C22: ='Tariff Database'!C25 | D22: ='Tariff Database'!D25 | E22: ='Tariff Database'!E25 | F22: ='Tariff Database'!K25 | G22: ='Tariff Database'!L25 | H22: ='Tariff Database'!M25 | I22: ='Tariff Database'!N25 | J22: ='Tariff Database'!O25 | K22: ='Tariff Database'!Y25 | L22: ='Tariff Database'!Z25 | M22: ='Tariff Database'!AB25 | N22: ='Tariff Database'!I25
A23: 22 | B23: ='Tariff Database'!B20 | C23: ='Tariff Database'!C20 | D23: ='Tariff Database'!D20 | E23: ='Tariff Database'!E20 | F23: ='Tariff Database'!K20 | G23: ='Tariff Database'!L20 | H23: ='Tariff Database'!M20 | I23: ='Tariff Database'!N20 | J23: ='Tariff Database'!O20 | K23: ='Tariff Database'!Y20 | L23: ='Tariff Database'!Z20 | M23: ='Tariff Database'!AB20 | N23: ='Tariff Database'!I20
A24: 23 | B24: ='Tariff Database'!B46 | C24: ='Tariff Database'!C46 | D24: ='Tariff Database'!D46 | E24: ='Tariff Database'!E46 | F24: ='Tariff Database'!K46 | G24: ='Tariff Database'!L46 | H24: ='Tariff Database'!M46 | I24: ='Tariff Database'!N46 | J24: ='Tariff Database'!O46 | K24: ='Tariff Database'!Y46 | L24: ='Tariff Database'!Z46 | M24: ='Tariff Database'!AB46 | N24: ='Tariff Database'!I46
A25: 24 | B25: ='Tariff Database'!B27 | C25: ='Tariff Database'!C27 | D25: ='Tariff Database'!D27 | E25: ='Tariff Database'!E27 | F25: ='Tariff Database'!K27 | G25: ='Tariff Database'!L27 | H25: ='Tariff Database'!M27 | I25: ='Tariff Database'!N27 | J25: ='Tariff Database'!O27 | K25: ='Tariff Database'!Y27 | L25: ='Tariff Database'!Z27 | M25: ='Tariff Database'!AB27 | N25: ='Tariff Database'!I27
A26: 25 | B26: ='Tariff Database'!B33 | C26: ='Tariff Database'!C33 | D26: ='Tariff Database'!D33 | E26: ='Tariff Database'!E33 | F26: ='Tariff Database'!K33 | G26: ='Tariff Database'!L33 | H26: ='Tariff Database'!M33 | I26: ='Tariff Database'!N33 | J26: ='Tariff Database'!O33 | K26: ='Tariff Database'!Y33 | L26: ='Tariff Database'!Z33 | M26: ='Tariff Database'!AB33 | N26: ='Tariff Database'!I33
A27: 26 | B27: ='Tariff Database'!B39 | C27: ='Tariff Database'!C39 | D27: ='Tariff Database'!D39 | E27: ='Tariff Database'!E39 | F27: ='Tariff Database'!K39 | G27: ='Tariff Database'!L39 | H27: ='Tariff Database'!M39 | I27: ='Tariff Database'!N39 | J27: ='Tariff Database'!O39 | K27: ='Tariff Database'!Y39 | L27: ='Tariff Database'!Z39 | M27: ='Tariff Database'!AB39 | N27: ='Tariff Database'!I39
A28: 27 | B28: ='Tariff Database'!B42 | C28: ='Tariff Database'!C42 | D28: ='Tariff Database'!D42 | E28: ='Tariff Database'!E42 | F28: ='Tariff Database'!K42 | G28: ='Tariff Database'!L42 | H28: ='Tariff Database'!M42 | I28: ='Tariff Database'!N42 | J28: ='Tariff Database'!O42 | K28: ='Tariff Database'!Y42 | L28: ='Tariff Database'!Z42 | M28: ='Tariff Database'!AB42 | N28: ='Tariff Database'!I42
A29: 28 | B29: ='Tariff Database'!B15 | C29: ='Tariff Database'!C15 | D29: ='Tariff Database'!D15 | E29: ='Tariff Database'!E15 | F29: ='Tariff Database'!K15 | G29: ='Tariff Database'!L15 | H29: ='Tariff Database'!M15 | I29: ='Tariff Database'!N15 | J29: ='Tariff Database'!O15 | K29: ='Tariff Database'!Y15 | L29: ='Tariff Database'!Z15 | M29: ='Tariff Database'!AB15 | N29: ='Tariff Database'!I15
A30: 29 | B30: ='Tariff Database'!B9 | C30: ='Tariff Database'!C9 | D30: ='Tariff Database'!D9 | E30: ='Tariff Database'!E9 | F30: ='Tariff Database'!K9 | G30: ='Tariff Database'!L9 | H30: ='Tariff Database'!M9 | I30: ='Tariff Database'!N9 | J30: ='Tariff Database'!O9 | K30: ='Tariff Database'!Y9 | L30: ='Tariff Database'!Z9 | M30: ='Tariff Database'!AB9 | N30: ='Tariff Database'!I9
A31: 30 | B31: ='Tariff Database'!B35 | C31: ='Tariff Database'!C35 | D31: ='Tariff Database'!D35 | E31: ='Tariff Database'!E35 | F31: ='Tariff Database'!K35 | G31: ='Tariff Database'!L35 | H31: ='Tariff Database'!M35 | I31: ='Tariff Database'!N35 | J31: ='Tariff Database'!O35 | K31: ='Tariff Database'!Y35 | L31: ='Tariff Database'!Z35 | M31: ='Tariff Database'!AB35 | N31: ='Tariff Database'!I35
A32: 31 | B32: ='Tariff Database'!B58 | C32: ='Tariff Database'!C58 | D32: ='Tariff Database'!D58 | E32: ='Tariff Database'!E58 | F32: ='Tariff Database'!K58 | G32: ='Tariff Database'!L58 | H32: ='Tariff Database'!M58 | I32: ='Tariff Database'!N58 | J32: ='Tariff Database'!O58 | K32: ='Tariff Database'!Y58 | L32: ='Tariff Database'!Z58 | M32: ='Tariff Database'!AB58 | N32: ='Tariff Database'!I58
A33: 32 | B33: ='Tariff Database'!B56 | C33: ='Tariff Database'!C56 | D33: ='Tariff Database'!D56 | E33: ='Tariff Database'!E56 | F33: ='Tariff Database'!K56 | G33: ='Tariff Database'!L56 | H33: ='Tariff Database'!M56 | I33: ='Tariff Database'!N56 | J33: ='Tariff Database'!O56 | K33: ='Tariff Database'!Y56 | L33: ='Tariff Database'!Z56 | M33: ='Tariff Database'!AB56 | N33: ='Tariff Database'!I56
A34: 33 | B34: ='Tariff Database'!B13 | C34: ='Tariff Database'!C13 | D34: ='Tariff Database'!D13 | E34: ='Tariff Database'!E13 | F34: ='Tariff Database'!K13 | G34: ='Tariff Database'!L13 | H34: ='Tariff Database'!M13 | I34: ='Tariff Database'!N13 | J34: ='Tariff Database'!O13 | K34: ='Tariff Database'!Y13 | L34: ='Tariff Database'!Z13 | M34: ='Tariff Database'!AB13 | N34: ='Tariff Database'!I13
A35: 34 | B35: ='Tariff Database'!B53 | C35: ='Tariff Database'!C53 | D35: ='Tariff Database'!D53 | E35: ='Tariff Database'!E53 | F35: ='Tariff Database'!K53 | G35: ='Tariff Database'!L53 | H35: ='Tariff Database'!M53 | I35: ='Tariff Database'!N53 | J35: ='Tariff Database'!O53 | K35: ='Tariff Database'!Y53 | L35: ='Tariff Database'!Z53 | M35: ='Tariff Database'!AB53 | N35: ='Tariff Database'!I53
A36: 35 | B36: ='Tariff Database'!B34 | C36: ='Tariff Database'!C34 | D36: ='Tariff Database'!D34 | E36: ='Tariff Database'!E34 | F36: ='Tariff Database'!K34 | G36: ='Tariff Database'!L34 | H36: ='Tariff Database'!M34 | I36: ='Tariff Database'!N34 | J36: ='Tariff Database'!O34 | K36: ='Tariff Database'!Y34 | L36: ='Tariff Database'!Z34 | M36: ='Tariff Database'!AB34 | N36: ='Tariff Database'!I34
A37: 36 | B37: ='Tariff Database'!B16 | C37: ='Tariff Database'!C16 | D37: ='Tariff Database'!D16 | E37: ='Tariff Database'!E16 | F37: ='Tariff Database'!K16 | G37: ='Tariff Database'!L16 | H37: ='Tariff Database'!M16 | I37: ='Tariff Database'!N16 | J37: ='Tariff Database'!O16 | K37: ='Tariff Database'!Y16 | L37: ='Tariff Database'!Z16 | M37: ='Tariff Database'!AB16 | N37: ='Tariff Database'!I16
A38: 37 | B38: ='Tariff Database'!B65 | C38: ='Tariff Database'!C65 | D38: ='Tariff Database'!D65 | E38: ='Tariff Database'!E65 | F38: ='Tariff Database'!K65 | G38: ='Tariff Database'!L65 | H38: ='Tariff Database'!M65 | I38: ='Tariff Database'!N65 | J38: ='Tariff Database'!O65 | K38: ='Tariff Database'!Y65 | L38: ='Tariff Database'!Z65 | M38: ='Tariff Database'!AB65 | N38: ='Tariff Database'!I65
A39: 38 | B39: ='Tariff Database'!B67 | C39: ='Tariff Database'!C67 | D39: ='Tariff Database'!D67 | E39: ='Tariff Database'!E67 | F39: ='Tariff Database'!K67 | G39: ='Tariff Database'!L67 | H39: ='Tariff Database'!M67 | I39: ='Tariff Database'!N67 | J39: ='Tariff Database'!O67 | K39: ='Tariff Database'!Y67 | L39: ='Tariff Database'!Z67 | M39: ='Tariff Database'!AB67 | N39: ='Tariff Database'!I67
A40: 39 | B40: ='Tariff Database'!B21 | C40: ='Tariff Database'!C21 | D40: ='Tariff Database'!D21 | E40: ='Tariff Database'!E21 | F40: ='Tariff Database'!K21 | G40: ='Tariff Database'!L21 | H40: ='Tariff Database'!M21 | I40: ='Tariff Database'!N21 | J40: ='Tariff Database'!O21 | K40: ='Tariff Database'!Y21 | L40: ='Tariff Database'!Z21 | M40: ='Tariff Database'!AB21 | N40: ='Tariff Database'!I21
A41: 40 | B41: ='Tariff Database'!B31 | C41: ='Tariff Database'!C31 | D41: ='Tariff Database'!D31 | E41: ='Tariff Database'!E31 | F41: ='Tariff Database'!K31 | G41: ='Tariff Database'!L31 | H41: ='Tariff Database'!M31 | I41: ='Tariff Database'!N31 | J41: ='Tariff Database'!O31 | K41: ='Tariff Database'!Y31 | L41: ='Tariff Database'!Z31 | M41: ='Tariff Database'!AB31 | N41: ='Tariff Database'!I31
A42: 41 | B42: ='Tariff Database'!B17 | C42: ='Tariff Database'!C17 | D42: ='Tariff Database'!D17 | E42: ='Tariff Database'!E17 | F42: ='Tariff Database'!K17 | G42: ='Tariff Database'!L17 | H42: ='Tariff Database'!M17 | I42: ='Tariff Database'!N17 | J42: ='Tariff Database'!O17 | K42: ='Tariff Database'!Y17 | L42: ='Tariff Database'!Z17 | M42: ='Tariff Database'!AB17 | N42: ='Tariff Database'!I17
A43: 42 | B43: ='Tariff Database'!B55 | C43: ='Tariff Database'!C55 | D43: ='Tariff Database'!D55 | E43: ='Tariff Database'!E55 | F43: ='Tariff Database'!K55 | G43: ='Tariff Database'!L55 | H43: ='Tariff Database'!M55 | I43: ='Tariff Database'!N55 | J43: ='Tariff Database'!O55 | K43: ='Tariff Database'!Y55 | L43: ='Tariff Database'!Z55 | M43: ='Tariff Database'!AB55 | N43: ='Tariff Database'!I55
A44: 43 | B44: ='Tariff Database'!B24 | C44: ='Tariff Database'!C24 | D44: ='Tariff Database'!D24 | E44: ='Tariff Database'!E24 | F44: ='Tariff Database'!K24 | G44: ='Tariff Database'!L24 | H44: ='Tariff Database'!M24 | I44: ='Tariff Database'!N24 | J44: ='Tariff Database'!O24 | K44: ='Tariff Database'!Y24 | L44: ='Tariff Database'!Z24 | M44: ='Tariff Database'!AB24 | N44: ='Tariff Database'!I24
A45: 44 | B45: ='Tariff Database'!B43 | C45: ='Tariff Database'!C43 | D45: ='Tariff Database'!D43 | E45: ='Tariff Database'!E43 | F45: ='Tariff Database'!K43 | G45: ='Tariff Database'!L43 | H45: ='Tariff Database'!M43 | I45: ='Tariff Database'!N43 | J45: ='Tariff Database'!O43 | K45: ='Tariff Database'!Y43 | L45: ='Tariff Database'!Z43 | M45: ='Tariff Database'!AB43 | N45: ='Tariff Database'!I43
A46: 45 | B46: ='Tariff Database'!B19 | C46: ='Tariff Database'!C19 | D46: ='Tariff Database'!D19 | E46: ='Tariff Database'!E19 | F46: ='Tariff Database'!K19 | G46: ='Tariff Database'!L19 | H46: ='Tariff Database'!M19 | I46: ='Tariff Database'!N19 | J46: ='Tariff Database'!O19 | K46: ='Tariff Database'!Y19 | L46: ='Tariff Database'!Z19 | M46: ='Tariff Database'!AB19 | N46: ='Tariff Database'!I19
A47: 46 | B47: ='Tariff Database'!B10 | C47: ='Tariff Database'!C10 | D47: ='Tariff Database'!D10 | E47: ='Tariff Database'!E10 | F47: ='Tariff Database'!K10 | G47: ='Tariff Database'!L10 | H47: ='Tariff Database'!M10 | I47: ='Tariff Database'!N10 | J47: ='Tariff Database'!O10 | K47: ='Tariff Database'!Y10 | L47: ='Tariff Database'!Z10 | M47: ='Tariff Database'!AB10 | N47: ='Tariff Database'!I10
A48: 47 | B48: ='Tariff Database'!B36 | C48: ='Tariff Database'!C36 | D48: ='Tariff Database'!D36 | E48: ='Tariff Database'!E36 | F48: ='Tariff Database'!K36 | G48: ='Tariff Database'!L36 | H48: ='Tariff Database'!M36 | I48: ='Tariff Database'!N36 | J48: ='Tariff Database'!O36 | K48: ='Tariff Database'!Y36 | L48: ='Tariff Database'!Z36 | M48: ='Tariff Database'!AB36 | N48: ='Tariff Database'!I36
A49: 48 | B49: ='Tariff Database'!B57 | C49: ='Tariff Database'!C57 | D49: ='Tariff Database'!D57 | E49: ='Tariff Database'!E57 | F49: ='Tariff Database'!K57 | G49: ='Tariff Database'!L57 | H49: ='Tariff Database'!M57 | I49: ='Tariff Database'!N57 | J49: ='Tariff Database'!O57 | K49: ='Tariff Database'!Y57 | L49: ='Tariff Database'!Z57 | M49: ='Tariff Database'!AB57 | N49: ='Tariff Database'!I57
A50: 49 | B50: ='Tariff Database'!B29 | C50: ='Tariff Database'!C29 | D50: ='Tariff Database'!D29 | E50: ='Tariff Database'!E29 | F50: ='Tariff Database'!K29 | G50: ='Tariff Database'!L29 | H50: ='Tariff Database'!M29 | I50: ='Tariff Database'!N29 | J50: ='Tariff Database'!O29 | K50: ='Tariff Database'!Y29 | L50: ='Tariff Database'!Z29 | M50: ='Tariff Database'!AB29 | N50: ='Tariff Database'!I29
A51: 50 | B51: ='Tariff Database'!B52 | C51: ='Tariff Database'!C52 | D51: ='Tariff Database'!D52 | E51: ='Tariff Database'!E52 | F51: ='Tariff Database'!K52 | G51: ='Tariff Database'!L52 | H51: ='Tariff Database'!M52 | I51: ='Tariff Database'!N52 | J51: ='Tariff Database'!O52 | K51: ='Tariff Database'!Y52 | L51: ='Tariff Database'!Z52 | M51: ='Tariff Database'!AB52 | N51: ='Tariff Database'!I52
A52: 51 | B52: ='Tariff Database'!B32 | C52: ='Tariff Database'!C32 | D52: ='Tariff Database'!D32 | E52: ='Tariff Database'!E32 | F52: ='Tariff Database'!K32 | G52: ='Tariff Database'!L32 | H52: ='Tariff Database'!M32 | I52: ='Tariff Database'!N32 | J52: ='Tariff Database'!O32 | K52: ='Tariff Database'!Y32 | L52: ='Tariff Database'!Z32 | M52: ='Tariff Database'!AB32 | N52: ='Tariff Database'!I32
A53: 52 | B53: ='Tariff Database'!B26 | C53: ='Tariff Database'!C26 | D53: ='Tariff Database'!D26 | E53: ='Tariff Database'!E26 | F53: ='Tariff Database'!K26 | G53: ='Tariff Database'!L26 | H53: ='Tariff Database'!M26 | I53: ='Tariff Database'!N26 | J53: ='Tariff Database'!O26 | K53: ='Tariff Database'!Y26 | L53: ='Tariff Database'!Z26 | M53: ='Tariff Database'!AB26 | N53: ='Tariff Database'!I26
A54: 53 | B54: ='Tariff Database'!B44 | C54: ='Tariff Database'!C44 | D54: ='Tariff Database'!D44 | E54: ='Tariff Database'!E44 | F54: ='Tariff Database'!K44 | G54: ='Tariff Database'!L44 | H54: ='Tariff Database'!M44 | I54: ='Tariff Database'!N44 | J54: ='Tariff Database'!O44 | K54: ='Tariff Database'!Y44 | L54: ='Tariff Database'!Z44 | M54: ='Tariff Database'!AB44 | N54: ='Tariff Database'!I44
A55: 54 | B55: ='Tariff Database'!B54 | C55: ='Tariff Database'!C54 | D55: ='Tariff Database'!D54 | E55: ='Tariff Database'!E54 | F55: ='Tariff Database'!K54 | G55: ='Tariff Database'!L54 | H55: ='Tariff Database'!M54 | I55: ='Tariff Database'!N54 | J55: ='Tariff Database'!O54 | K55: ='Tariff Database'!Y54 | L55: ='Tariff Database'!Z54 | M55: ='Tariff Database'!AB54 | N55: ='Tariff Database'!I54
A56: 55 | B56: ='Tariff Database'!B28 | C56: ='Tariff Database'!C28 | D56: ='Tariff Database'!D28 | E56: ='Tariff Database'!E28 | F56: ='Tariff Database'!K28 | G56: ='Tariff Database'!L28 | H56: ='Tariff Database'!M28 | I56: ='Tariff Database'!N28 | J56: ='Tariff Database'!O28 | K56: ='Tariff Database'!Y28 | L56: ='Tariff Database'!Z28 | M56: ='Tariff Database'!AB28 | N56: ='Tariff Database'!I28
A57: 56 | B57: ='Tariff Database'!B64 | C57: ='Tariff Database'!C64 | D57: ='Tariff Database'!D64 | E57: ='Tariff Database'!E64 | F57: ='Tariff Database'!K64 | G57: ='Tariff Database'!L64 | H57: ='Tariff Database'!M64 | I57: ='Tariff Database'!N64 | J57: ='Tariff Database'!O64 | K57: ='Tariff Database'!Y64 | L57: ='Tariff Database'!Z64 | M57: ='Tariff Database'!AB64 | N57: ='Tariff Database'!I64
A58: 57 | B58: ='Tariff Database'!B66 | C58: ='Tariff Database'!C66 | D58: ='Tariff Database'!D66 | E58: ='Tariff Database'!E66 | F58: ='Tariff Database'!K66 | G58: ='Tariff Database'!L66 | H58: ='Tariff Database'!M66 | I58: ='Tariff Database'!N66 | J58: ='Tariff Database'!O66 | K58: ='Tariff Database'!Y66 | L58: ='Tariff Database'!Z66 | M58: ='Tariff Database'!AB66 | N58: ='Tariff Database'!I66
A59: 58 | B59: ='Tariff Database'!B30 | C59: ='Tariff Database'!C30 | D59: ='Tariff Database'!D30 | E59: ='Tariff Database'!E30 | F59: ='Tariff Database'!K30 | G59: ='Tariff Database'!L30 | H59: ='Tariff Database'!M30 | I59: ='Tariff Database'!N30 | J59: ='Tariff Database'!O30 | K59: ='Tariff Database'!Y30 | L59: ='Tariff Database'!Z30 | M59: ='Tariff Database'!AB30 | N59: ='Tariff Database'!I30
A60: 59 | B60: ='Tariff Database'!B14 | C60: ='Tariff Database'!C14 | D60: ='Tariff Database'!D14 | E60: ='Tariff Database'!E14 | F60: ='Tariff Database'!K14 | G60: ='Tariff Database'!L14 | H60: ='Tariff Database'!M14 | I60: ='Tariff Database'!N14 | J60: ='Tariff Database'!O14 | K60: ='Tariff Database'!Y14 | L60: ='Tariff Database'!Z14 | M60: ='Tariff Database'!AB14 | N60: ='Tariff Database'!I14
A61: 60 | B61: ='Tariff Database'!B63 | C61: ='Tariff Database'!C63 | D61: ='Tariff Database'!D63 | E61: ='Tariff Database'!E63 | F61: ='Tariff Database'!K63 | G61: ='Tariff Database'!L63 | H61: ='Tariff Database'!M63 | I61: ='Tariff Database'!N63 | J61: ='Tariff Database'!O63 | K61: ='Tariff Database'!Y63 | L61: ='Tariff Database'!Z63 | M61: ='Tariff Database'!AB63 | N61: ='Tariff Database'!I63
A62: 61 | B62: ='Tariff Database'!B69 | C62: ='Tariff Database'!C69 | D62: ='Tariff Database'!D69 | E62: ='Tariff Database'!E69 | F62: ='Tariff Database'!K69 | G62: ='Tariff Database'!L69 | H62: ='Tariff Database'!M69 | I62: ='Tariff Database'!N69 | J62: ='Tariff Database'!O69 | K62: ='Tariff Database'!Y69 | L62: ='Tariff Database'!Z69 | M62: ='Tariff Database'!AB69 | N62: ='Tariff Database'!I69
A63: 62 | B63: ='Tariff Database'!B62 | C63: ='Tariff Database'!C62 | D63: ='Tariff Database'!D62 | E63: ='Tariff Database'!E62 | F63: ='Tariff Database'!K62 | G63: ='Tariff Database'!L62 | H63: ='Tariff Database'!M62 | I63: ='Tariff Database'!N62 | J63: ='Tariff Database'!O62 | K63: ='Tariff Database'!Y62 | L63: ='Tariff Database'!Z62 | M63: ='Tariff Database'!AB62 | N63: ='Tariff Database'!I62
A64: 63 | B64: ='Tariff Database'!B41 | C64: ='Tariff Database'!C41 | D64: ='Tariff Database'!D41 | E64: ='Tariff Database'!E41 | F64: ='Tariff Database'!K41 | G64: ='Tariff Database'!L41 | H64: ='Tariff Database'!M41 | I64: ='Tariff Database'!N41 | J64: ='Tariff Database'!O41 | K64: ='Tariff Database'!Y41 | L64: ='Tariff Database'!Z41 | M64: ='Tariff Database'!AB41 | N64: ='Tariff Database'!I41
A65: 64 | B65: ='Tariff Database'!B74 | C65: ='Tariff Database'!C74 | D65: ='Tariff Database'!D74 | E65: ='Tariff Database'!E74 | F65: ='Tariff Database'!K74 | G65: ='Tariff Database'!L74 | H65: ='Tariff Database'!M74 | I65: ='Tariff Database'!N74 | J65: ='Tariff Database'!O74 | K65: ='Tariff Database'!Y74 | L65: ='Tariff Database'!Z74 | M65: ='Tariff Database'!AB74 | N65: ='Tariff Database'!I74
A66: 65 | B66: ='Tariff Database'!B70 | C66: ='Tariff Database'!C70 | D66: ='Tariff Database'!D70 | E66: ='Tariff Database'!E70 | F66: ='Tariff Database'!K70 | G66: ='Tariff Database'!L70 | H66: ='Tariff Database'!M70 | I66: ='Tariff Database'!N70 | J66: ='Tariff Database'!O70 | K66: ='Tariff Database'!Y70 | L66: ='Tariff Database'!Z70 | M66: ='Tariff Database'!AB70 | N66: ='Tariff Database'!I70
A67: 66 | B67: ='Tariff Database'!B72 | C67: ='Tariff Database'!C72 | D67: ='Tariff Database'!D72 | E67: ='Tariff Database'!E72 | F67: ='Tariff Database'!K72 | G67: ='Tariff Database'!L72 | H67: ='Tariff Database'!M72 | I67: ='Tariff Database'!N72 | J67: ='Tariff Database'!O72 | K67: ='Tariff Database'!Y72 | L67: ='Tariff Database'!Z72 | M67: ='Tariff Database'!AB72 | N67: ='Tariff Database'!I72
A68: 67 | B68: ='Tariff Database'!B73 | C68: ='Tariff Database'!C73 | D68: ='Tariff Database'!D73 | E68: ='Tariff Database'!E73 | F68: ='Tariff Database'!K73 | G68: ='Tariff Database'!L73 | H68: ='Tariff Database'!M73 | I68: ='Tariff Database'!N73 | J68: ='Tariff Database'!O73 | K68: ='Tariff Database'!Y73 | L68: ='Tariff Database'!Z73 | M68: ='Tariff Database'!AB73 | N68: ='Tariff Database'!I73
A69: 68 | B69: ='Tariff Database'!B61 | C69: ='Tariff Database'!C61 | D69: ='Tariff Database'!D61 | E69: ='Tariff Database'!E61 | F69: ='Tariff Database'!K61 | G69: ='Tariff Database'!L61 | H69: ='Tariff Database'!M61 | I69: ='Tariff Database'!N61 | J69: ='Tariff Database'!O61 | K69: ='Tariff Database'!Y61 | L69: ='Tariff Database'!Z61 | M69: ='Tariff Database'!AB61 | N69: ='Tariff Database'!I61
A70: 69 | B70: ='Tariff Database'!B71 | C70: ='Tariff Database'!C71 | D70: ='Tariff Database'!D71 | E70: ='Tariff Database'!E71 | F70: ='Tariff Database'!K71 | G70: ='Tariff Database'!L71 | H70: ='Tariff Database'!M71 | I70: ='Tariff Database'!N71 | J70: ='Tariff Database'!O71 | K70: ='Tariff Database'!Y71 | L70: ='Tariff Database'!Z71 | M70: ='Tariff Database'!AB71 | N70: ='Tariff Database'!I71
A71: 70 | B71: ='Tariff Database'!B60 | C71: ='Tariff Database'!C60 | D71: ='Tariff Database'!D60 | E71: ='Tariff Database'!E60 | F71: ='Tariff Database'!K60 | G71: ='Tariff Database'!L60 | H71: ='Tariff Database'!M60 | I71: ='Tariff Database'!N60 | J71: ='Tariff Database'!O60 | K71: ='Tariff Database'!Y60 | L71: ='Tariff Database'!Z60 | M71: ='Tariff Database'!AB60 | N71: ='Tariff Database'!I60
A72: 71 | B72: ='Tariff Database'!B68 | C72: ='Tariff Database'!C68 | D72: ='Tariff Database'!D68 | E72: ='Tariff Database'!E68 | F72: ='Tariff Database'!K68 | G72: ='Tariff Database'!L68 | H72: ='Tariff Database'!M68 | I72: ='Tariff Database'!N68 | J72: ='Tariff Database'!O68 | K72: ='Tariff Database'!Y68 | L72: ='Tariff Database'!Z68 | M72: ='Tariff Database'!AB68 | N72: ='Tariff Database'!I68
A73: 72 | B73: ='Tariff Database'!B59 | C73: ='Tariff Database'!C59 | D73: ='Tariff Database'!D59 | E73: ='Tariff Database'!E59 | F73: ='Tariff Database'!K59 | G73: ='Tariff Database'!L59 | H73: ='Tariff Database'!M59 | I73: ='Tariff Database'!N59 | J73: ='Tariff Database'!O59 | K73: ='Tariff Database'!Y59 | L73: ='Tariff Database'!Z59 | M73: ='Tariff Database'!AB59 | N73: ='Tariff Database'!I59
A74: 73 | B74: ='Tariff Database'!B75 | C74: ='Tariff Database'!C75 | D74: ='Tariff Database'!D75 | E74: ='Tariff Database'!E75 | F74: ='Tariff Database'!K75 | G74: ='Tariff Database'!L75 | H74: ='Tariff Database'!M75 | I74: ='Tariff Database'!N75 | J74: ='Tariff Database'!O75 | K74: ='Tariff Database'!Y75 | L74: ='Tariff Database'!Z75 | M74: ='Tariff Database'!AB75 | N74: ='Tariff Database'!I75
A75: 74 | B75: ='Tariff Database'!B76 | C75: ='Tariff Database'!C76 | D75: ='Tariff Database'!D76 | E75: ='Tariff Database'!E76 | F75: ='Tariff Database'!K76 | G75: ='Tariff Database'!L76 | H75: ='Tariff Database'!M76 | I75: ='Tariff Database'!N76 | J75: ='Tariff Database'!O76 | K75: ='Tariff Database'!Y76 | L75: ='Tariff Database'!Z76 | M75: ='Tariff Database'!AB76 | N75: ='Tariff Database'!I76
A76: 75 | B76: ='Tariff Database'!B77 | C76: ='Tariff Database'!C77 | D76: ='Tariff Database'!D77 | E76: ='Tariff Database'!E77 | F76: ='Tariff Database'!K77 | G76: ='Tariff Database'!L77 | H76: ='Tariff Database'!M77 | I76: ='Tariff Database'!N77 | J76: ='Tariff Database'!O77 | K76: ='Tariff Database'!Y77 | L76: ='Tariff Database'!Z77 | M76: ='Tariff Database'!AB77 | N76: ='Tariff Database'!I77
A77: 76 | B77: ='Tariff Database'!B78 | C77: ='Tariff Database'!C78 | D77: ='Tariff Database'!D78 | E77: ='Tariff Database'!E78 | F77: ='Tariff Database'!K78 | G77: ='Tariff Database'!L78 | H77: ='Tariff Database'!M78 | I77: ='Tariff Database'!N78 | J77: ='Tariff Database'!O78 | K77: ='Tariff Database'!Y78 | L77: ='Tariff Database'!Z78 | M77: ='Tariff Database'!AB78 | N77: ='Tariff Database'!I78
A78: 77 | B78: ='Tariff Database'!B79 | C78: ='Tariff Database'!C79 | D78: ='Tariff Database'!D79 | E78: ='Tariff Database'!E79 | F78: ='Tariff Database'!K79 | G78: ='Tariff Database'!L79 | H78: ='Tariff Database'!M79 | I78: ='Tariff Database'!N79 | J78: ='Tariff Database'!O79 | K78: ='Tariff Database'!Y79 | L78: ='Tariff Database'!Z79 | M78: ='Tariff Database'!AB79 | N78: ='Tariff Database'!I79
A79: 78 | B79: ='Tariff Database'!B80 | C79: ='Tariff Database'!C80 | D79: ='Tariff Database'!D80 | E79: ='Tariff Database'!E80 | F79: ='Tariff Database'!K80 | G79: ='Tariff Database'!L80 | H79: ='Tariff Database'!M80 | I79: ='Tariff Database'!N80 | J79: ='Tariff Database'!O80 | K79: ='Tariff Database'!Y80 | L79: ='Tariff Database'!Z80 | M79: ='Tariff Database'!AB80 | N79: ='Tariff Database'!I80
A80: 79 | B80: ='Tariff Database'!B81 | C80: ='Tariff Database'!C81 | D80: ='Tariff Database'!D81 | E80: ='Tariff Database'!E81 | F80: ='Tariff Database'!K81 | G80: ='Tariff Database'!L81 | H80: ='Tariff Database'!M81 | I80: ='Tariff Database'!N81 | J80: ='Tariff Database'!O81 | K80: ='Tariff Database'!Y81 | L80: ='Tariff Database'!Z81 | M80: ='Tariff Database'!AB81 | N80: ='Tariff Database'!I81
A81: 80 | B81: ='Tariff Database'!B82 | C81: ='Tariff Database'!C82 | D81: ='Tariff Database'!D82 | E81: ='Tariff Database'!E82 | F81: ='Tariff Database'!K82 | G81: ='Tariff Database'!L82 | H81: ='Tariff Database'!M82 | I81: ='Tariff Database'!N82 | J81: ='Tariff Database'!O82 | K81: ='Tariff Database'!Y82 | L81: ='Tariff Database'!Z82 | M81: ='Tariff Database'!AB82 | N81: ='Tariff Database'!I82
A82: 81 | B82: ='Tariff Database'!B83 | C82: ='Tariff Database'!C83 | D82: ='Tariff Database'!D83 | E82: ='Tariff Database'!E83 | F82: ='Tariff Database'!K83 | G82: ='Tariff Database'!L83 | H82: ='Tariff Database'!M83 | I82: ='Tariff Database'!N83 | J82: ='Tariff Database'!O83 | K82: ='Tariff Database'!Y83 | L82: ='Tariff Database'!Z83 | M82: ='Tariff Database'!AB83 | N82: ='Tariff Database'!I83
A83: 82 | B83: ='Tariff Database'!B84 | C83: ='Tariff Database'!C84 | D83: ='Tariff Database'!D84 | E83: ='Tariff Database'!E84 | F83: ='Tariff Database'!K84 | G83: ='Tariff Database'!L84 | H83: ='Tariff Database'!M84 | I83: ='Tariff Database'!N84 | J83: ='Tariff Database'!O84 | K83: ='Tariff Database'!Y84 | L83: ='Tariff Database'!Z84 | M83: ='Tariff Database'!AB84 | N83: ='Tariff Database'!I84
A84: 83 | B84: ='Tariff Database'!B85 | C84: ='Tariff Database'!C85 | D84: ='Tariff Database'!D85 | E84: ='Tariff Database'!E85 | F84: ='Tariff Database'!K85 | G84: ='Tariff Database'!L85 | H84: ='Tariff Database'!M85 | I84: ='Tariff Database'!N85 | J84: ='Tariff Database'!O85 | K84: ='Tariff Database'!Y85 | L84: ='Tariff Database'!Z85 | M84: ='Tariff Database'!AB85 | N84: ='Tariff Database'!I85
A85: 84 | B85: ='Tariff Database'!B86 | C85: ='Tariff Database'!C86 | D85: ='Tariff Database'!D86 | E85: ='Tariff Database'!E86 | F85: ='Tariff Database'!K86 | G85: ='Tariff Database'!L86 | H85: ='Tariff Database'!M86 | I85: ='Tariff Database'!N86 | J85: ='Tariff Database'!O86 | K85: ='Tariff Database'!Y86 | L85: ='Tariff Database'!Z86 | M85: ='Tariff Database'!AB86 | N85: ='Tariff Database'!I86
... A89: 88 | B89: ='Tariff Database'!B90 | C89: ='Tariff Database'!C90 | D89: ='Tariff Database'!D90 | E89: ='Tariff Database'!E90 | F89: ='Tariff Database'!K90 | G89: ='Tariff Database'!L90 | H89: ='Tariff Database'!M90 | I89: ='Tariff Database'!N90 | J89: ='Tariff Database'!O90 | K89: ='Tariff Database'!Y90 | L89: ='Tariff Database'!Z90 | M89: ='Tariff Database'!AB90 | N89: ='Tariff Database'!I90

Sheet Protection Matrix
A1: Rank | B1: Utility | C1: State | D1: Min Load (MW) | E1: Ratchet % | F1: Contract (Yrs) | G1: CIAC | H1: Take-or-Pay | I1: Exit Fee | J1: Demand Ratchet | K1: Credit Req | L1: DC Specific | M1: Collateral | N1: Score | O1: Rating
A2: 1 | B2: ='Tariff Database'!B14 | C2: ='Tariff Database'!C14 | D2: ='Tariff Database'!J14 | E2: ='Tariff Database'!Q14 | F2: ='Tariff Database'!P14 | G2: ='Tariff Database'!S14 | H2: ='Tariff Database'!T14 | I2: ='Tariff Database'!U14 | J2: ='Tariff Database'!R14 | K2: ='Tariff Database'!V14 | L2: ='Tariff Database'!W14 | M2: ='Tariff Database'!X14 | N2: ='Tariff Database'!AA14 | O2: ='Tariff Database'!AB14
A3: 2 | B3: ='Tariff Database'!B19 | C3: ='Tariff Database'!C19 | D3: ='Tariff Database'!J19 | E3: ='Tariff Database'!Q19 | F3: ='Tariff Database'!P19 | G3: ='Tariff Database'!S19 | H3: ='Tariff Database'!T19 | I3: ='Tariff Database'!U19 | J3: ='Tariff Database'!R19 | K3: ='Tariff Database'!V19 | L3: ='Tariff Database'!W19 | M3: ='Tariff Database'!X19 | N3: ='Tariff Database'!AA19 | O3: ='Tariff Database'!AB19
A4: 3 | B4: ='Tariff Database'!B24 | C4: ='Tariff Database'!C24 | D4: ='Tariff Database'!J24 | E4: ='Tariff Database'!Q24 | F4: ='Tariff Database'!P24 | G4: ='Tariff Database'!S24 | H4: ='Tariff Database'!T24 | I4: ='Tariff Database'!U24 | J4: ='Tariff Database'!R24 | K4: ='Tariff Database'!V24 | L4: ='Tariff Database'!W24 | M4: ='Tariff Database'!X24 | N4: ='Tariff Database'!AA24 | O4: ='Tariff Database'!AB24
A5: 4 | B5: ='Tariff Database'!B38 | C5: ='Tariff Database'!C38 | D5: ='Tariff Database'!J38 | E5: ='Tariff Database'!Q38 | F5: ='Tariff Database'!P38 | G5: ='Tariff Database'!S38 | H5: ='Tariff Database'!T38 | I5: ='Tariff Database'!U38 | J5: ='Tariff Database'!R38 | K5: ='Tariff Database'!V38 | L5: ='Tariff Database'!W38 | M5: ='Tariff Database'!X38 | N5: ='Tariff Database'!AA38 | O5: ='Tariff Database'!AB38
A6: 5 | B6: ='Tariff Database'!B39 | C6: ='Tariff Database'!C39 | D6: ='Tariff Database'!J39 | E6: ='Tariff Database'!Q39 | F6: ='Tariff Database'!P39 | G6: ='Tariff Database'!S39 | H6: ='Tariff Database'!T39 | I6: ='Tariff Database'!U39 | J6: ='Tariff Database'!R39 | K6: ='Tariff Database'!V39 | L6: ='Tariff Database'!W39 | M6: ='Tariff Database'!X39 | N6: ='Tariff Database'!AA39 | O6: ='Tariff Database'!AB39
A7: 6 | B7: ='Tariff Database'!B44 | C7: ='Tariff Database'!C44 | D7: ='Tariff Database'!J44 | E7: ='Tariff Database'!Q44 | F7: ='Tariff Database'!P44 | G7: ='Tariff Database'!S44 | H7: ='Tariff Database'!T44 | I7: ='Tariff Database'!U44 | J7: ='Tariff Database'!R44 | K7: ='Tariff Database'!V44 | L7: ='Tariff Database'!W44 | M7: ='Tariff Database'!X44 | N7: ='Tariff Database'!AA44 | O7: ='Tariff Database'!AB44
A8: 7 | B8: ='Tariff Database'!B5 | C8: ='Tariff Database'!C5 | D8: ='Tariff Database'!J5 | E8: ='Tariff Database'!Q5 | F8: ='Tariff Database'!P5 | G8: ='Tariff Database'!S5 | H8: ='Tariff Database'!T5 | I8: ='Tariff Database'!U5 | J8: ='Tariff Database'!R5 | K8: ='Tariff Database'!V5 | L8: ='Tariff Database'!W5 | M8: ='Tariff Database'!X5 | N8: ='Tariff Database'!AA5 | O8: ='Tariff Database'!AB5
A9: 8 | B9: ='Tariff Database'!B13 | C9: ='Tariff Database'!C13 | D9: ='Tariff Database'!J13 | E9: ='Tariff Database'!Q13 | F9: ='Tariff Database'!P13 | G9: ='Tariff Database'!S13 | H9: ='Tariff Database'!T13 | I9: ='Tariff Database'!U13 | J9: ='Tariff Database'!R13 | K9: ='Tariff Database'!V13 | L9: ='Tariff Database'!W13 | M9: ='Tariff Database'!X13 | N9: ='Tariff Database'!AA13 | O9: ='Tariff Database'!AB13
A10: 9 | B10: ='Tariff Database'!B30 | C10: ='Tariff Database'!C30 | D10: ='Tariff Database'!J30 | E10: ='Tariff Database'!Q30 | F10: ='Tariff Database'!P30 | G10: ='Tariff Database'!S30 | H10: ='Tariff Database'!T30 | I10: ='Tariff Database'!U30 | J10: ='Tariff Database'!R30 | K10: ='Tariff Database'!V30 | L10: ='Tariff Database'!W30 | M10: ='Tariff Database'!X30 | N10: ='Tariff Database'!AA30 | O10: ='Tariff Database'!AB30
A11: 10 | B11: ='Tariff Database'!B37 | C11: ='Tariff Database'!C37 | D11: ='Tariff Database'!J37 | E11: ='Tariff Database'!Q37 | F11: ='Tariff Database'!P37 | G11: ='Tariff Database'!S37 | H11: ='Tariff Database'!T37 | I11: ='Tariff Database'!U37 | J11: ='Tariff Database'!R37 | K11: ='Tariff Database'!V37 | L11: ='Tariff Database'!W37 | M11: ='Tariff Database'!X37 | N11: ='Tariff Database'!AA37 | O11: ='Tariff Database'!AB37
A12: 11 | B12: ='Tariff Database'!B40 | C12: ='Tariff Database'!C40 | D12: ='Tariff Database'!J40 | E12: ='Tariff Database'!Q40 | F12: ='Tariff Database'!P40 | G12: ='Tariff Database'!S40 | H12: ='Tariff Database'!T40 | I12: ='Tariff Database'!U40 | J12: ='Tariff Database'!R40 | K12: ='Tariff Database'!V40 | L12: ='Tariff Database'!W40 | M12: ='Tariff Database'!X40 | N12: ='Tariff Database'!AA40 | O12: ='Tariff Database'!AB40
A13: 12 | B13: ='Tariff Database'!B43 | C13: ='Tariff Database'!C43 | D13: ='Tariff Database'!J43 | E13: ='Tariff Database'!Q43 | F13: ='Tariff Database'!P43 | G13: ='Tariff Database'!S43 | H13: ='Tariff Database'!T43 | I13: ='Tariff Database'!U43 | J13: ='Tariff Database'!R43 | K13: ='Tariff Database'!V43 | L13: ='Tariff Database'!W43 | M13: ='Tariff Database'!X43 | N13: ='Tariff Database'!AA43 | O13: ='Tariff Database'!AB43
A14: 13 | B14: ='Tariff Database'!B22 | C14: ='Tariff Database'!C22 | D14: ='Tariff Database'!J22 | E14: ='Tariff Database'!Q22 | F14: ='Tariff Database'!P22 | G14: ='Tariff Database'!S22 | H14: ='Tariff Database'!T22 | I14: ='Tariff Database'!U22 | J14: ='Tariff Database'!R22 | K14: ='Tariff Database'!V22 | L14: ='Tariff Database'!W22 | M14: ='Tariff Database'!X22 | N14: ='Tariff Database'!AA22 | O14: ='Tariff Database'!AB22
A15: 14 | B15: ='Tariff Database'!B23 | C15: ='Tariff Database'!C23 | D15: ='Tariff Database'!J23 | E15: ='Tariff Database'!Q23 | F15: ='Tariff Database'!P23 | G15: ='Tariff Database'!S23 | H15: ='Tariff Database'!T23 | I15: ='Tariff Database'!U23 | J15: ='Tariff Database'!R23 | K15: ='Tariff Database'!V23 | L15: ='Tariff Database'!W23 | M15: ='Tariff Database'!X23 | N15: ='Tariff Database'!AA23 | O15: ='Tariff Database'!AB23
A16: 15 | B16: ='Tariff Database'!B41 | C16: ='Tariff Database'!C41 | D16: ='Tariff Database'!J41 | E16: ='Tariff Database'!Q41 | F16: ='Tariff Database'!P41 | G16: ='Tariff Database'!S41 | H16: ='Tariff Database'!T41 | I16: ='Tariff Database'!U41 | J16: ='Tariff Database'!R41 | K16: ='Tariff Database'!V41 | L16: ='Tariff Database'!W41 | M16: ='Tariff Database'!X41 | N16: ='Tariff Database'!AA41 | O16: ='Tariff Database'!AB41
A17: 16 | B17: ='Tariff Database'!B52 | C17: ='Tariff Database'!C52 | D17: ='Tariff Database'!J52 | E17: ='Tariff Database'!Q52 | F17: ='Tariff Database'!P52 | G17: ='Tariff Database'!S52 | H17: ='Tariff Database'!T52 | I17: ='Tariff Database'!U52 | J17: ='Tariff Database'!R52 | K17: ='Tariff Database'!V52 | L17: ='Tariff Database'!W52 | M17: ='Tariff Database'!X52 | N17: ='Tariff Database'!AA52 | O17: ='Tariff Database'!AB52
A18: 17 | B18: ='Tariff Database'!B11 | C18: ='Tariff Database'!C11 | D18: ='Tariff Database'!J11 | E18: ='Tariff Database'!Q11 | F18: ='Tariff Database'!P11 | G18: ='Tariff Database'!S11 | H18: ='Tariff Database'!T11 | I18: ='Tariff Database'!U11 | J18: ='Tariff Database'!R11 | K18: ='Tariff Database'!V11 | L18: ='Tariff Database'!W11 | M18: ='Tariff Database'!X11 | N18: ='Tariff Database'!AA11 | O18: ='Tariff Database'!AB11
A19: 18 | B19: ='Tariff Database'!B3 | C19: ='Tariff Database'!C3 | D19: ='Tariff Database'!J3 | E19: ='Tariff Database'!Q3 | F19: ='Tariff Database'!P3 | G19: ='Tariff Database'!S3 | H19: ='Tariff Database'!T3 | I19: ='Tariff Database'!U3 | J19: ='Tariff Database'!R3 | K19: ='Tariff Database'!V3 | L19: ='Tariff Database'!W3 | M19: ='Tariff Database'!X3 | N19: ='Tariff Database'!AA3 | O19: ='Tariff Database'!AB3
A20: 19 | B20: ='Tariff Database'!B25 | C20: ='Tariff Database'!C25 | D20: ='Tariff Database'!J25 | E20: ='Tariff Database'!Q25 | F20: ='Tariff Database'!P25 | G20: ='Tariff Database'!S25 | H20: ='Tariff Database'!T25 | I20: ='Tariff Database'!U25 | J20: ='Tariff Database'!R25 | K20: ='Tariff Database'!V25 | L20: ='Tariff Database'!W25 | M20: ='Tariff Database'!X25 | N20: ='Tariff Database'!AA25 | O20: ='Tariff Database'!AB25
A21: 20 | B21: ='Tariff Database'!B6 | C21: ='Tariff Database'!C6 | D21: ='Tariff Database'!J6 | E21: ='Tariff Database'!Q6 | F21: ='Tariff Database'!P6 | G21: ='Tariff Database'!S6 | H21: ='Tariff Database'!T6 | I21: ='Tariff Database'!U6 | J21: ='Tariff Database'!R6 | K21: ='Tariff Database'!V6 | L21: ='Tariff Database'!W6 | M21: ='Tariff Database'!X6 | N21: ='Tariff Database'!AA6 | O21: ='Tariff Database'!AB6
A22: 21 | B22: ='Tariff Database'!B12 | C22: ='Tariff Database'!C12 | D22: ='Tariff Database'!J12 | E22: ='Tariff Database'!Q12 | F22: ='Tariff Database'!P12 | G22: ='Tariff Database'!S12 | H22: ='Tariff Database'!T12 | I22: ='Tariff Database'!U12 | J22: ='Tariff Database'!R12 | K22: ='Tariff Database'!V12 | L22: ='Tariff Database'!W12 | M22: ='Tariff Database'!X12 | N22: ='Tariff Database'!AA12 | O22: ='Tariff Database'!AB12
A23: 22 | B23: ='Tariff Database'!B15 | C23: ='Tariff Database'!C15 | D23: ='Tariff Database'!J15 | E23: ='Tariff Database'!Q15 | F23: ='Tariff Database'!P15 | G23: ='Tariff Database'!S15 | H23: ='Tariff Database'!T15 | I23: ='Tariff Database'!U15 | J23: ='Tariff Database'!R15 | K23: ='Tariff Database'!V15 | L23: ='Tariff Database'!W15 | M23: ='Tariff Database'!X15 | N23: ='Tariff Database'!AA15 | O23: ='Tariff Database'!AB15
A24: 23 | B24: ='Tariff Database'!B16 | C24: ='Tariff Database'!C16 | D24: ='Tariff Database'!J16 | E24: ='Tariff Database'!Q16 | F24: ='Tariff Database'!P16 | G24: ='Tariff Database'!S16 | H24: ='Tariff Database'!T16 | I24: ='Tariff Database'!U16 | J24: ='Tariff Database'!R16 | K24: ='Tariff Database'!V16 | L24: ='Tariff Database'!W16 | M24: ='Tariff Database'!X16 | N24: ='Tariff Database'!AA16 | O24: ='Tariff Database'!AB16
A25: 24 | B25: ='Tariff Database'!B53 | C25: ='Tariff Database'!C53 | D25: ='Tariff Database'!J53 | E25: ='Tariff Database'!Q53 | F25: ='Tariff Database'!P53 | G25: ='Tariff Database'!S53 | H25: ='Tariff Database'!T53 | I25: ='Tariff Database'!U53 | J25: ='Tariff Database'!R53 | K25: ='Tariff Database'!V53 | L25: ='Tariff Database'!W53 | M25: ='Tariff Database'!X53 | N25: ='Tariff Database'!AA53 | O25: ='Tariff Database'!AB53
A26: 25 | B26: ='Tariff Database'!B64 | C26: ='Tariff Database'!C64 | D26: ='Tariff Database'!J64 | E26: ='Tariff Database'!Q64 | F26: ='Tariff Database'!P64 | G26: ='Tariff Database'!S64 | H26: ='Tariff Database'!T64 | I26: ='Tariff Database'!U64 | J26: ='Tariff Database'!R64 | K26: ='Tariff Database'!V64 | L26: ='Tariff Database'!W64 | M26: ='Tariff Database'!X64 | N26: ='Tariff Database'!AA64 | O26: ='Tariff Database'!AB64
A27: 26 | B27: ='Tariff Database'!B9 | C27: ='Tariff Database'!C9 | D27: ='Tariff Database'!J9 | E27: ='Tariff Database'!Q9 | F27: ='Tariff Database'!P9 | G27: ='Tariff Database'!S9 | H27: ='Tariff Database'!T9 | I27: ='Tariff Database'!U9 | J27: ='Tariff Database'!R9 | K27: ='Tariff Database'!V9 | L27: ='Tariff Database'!W9 | M27: ='Tariff Database'!X9 | N27: ='Tariff Database'!AA9 | O27: ='Tariff Database'!AB9
A28: 27 | B28: ='Tariff Database'!B10 | C28: ='Tariff Database'!C10 | D28: ='Tariff Database'!J10 | E28: ='Tariff Database'!Q10 | F28: ='Tariff Database'!P10 | G28: ='Tariff Database'!S10 | H28: ='Tariff Database'!T10 | I28: ='Tariff Database'!U10 | J28: ='Tariff Database'!R10 | K28: ='Tariff Database'!V10 | L28: ='Tariff Database'!W10 | M28: ='Tariff Database'!X10 | N28: ='Tariff Database'!AA10 | O28: ='Tariff Database'!AB10
A29: 28 | B29: ='Tariff Database'!B17 | C29: ='Tariff Database'!C17 | D29: ='Tariff Database'!J17 | E29: ='Tariff Database'!Q17 | F29: ='Tariff Database'!P17 | G29: ='Tariff Database'!S17 | H29: ='Tariff Database'!T17 | I29: ='Tariff Database'!U17 | J29: ='Tariff Database'!R17 | K29: ='Tariff Database'!V17 | L29: ='Tariff Database'!W17 | M29: ='Tariff Database'!X17 | N29: ='Tariff Database'!AA17 | O29: ='Tariff Database'!AB17
A30: 29 | B30: ='Tariff Database'!B18 | C30: ='Tariff Database'!C18 | D30: ='Tariff Database'!J18 | E30: ='Tariff Database'!Q18 | F30: ='Tariff Database'!P18 | G30: ='Tariff Database'!S18 | H30: ='Tariff Database'!T18 | I30: ='Tariff Database'!U18 | J30: ='Tariff Database'!R18 | K30: ='Tariff Database'!V18 | L30: ='Tariff Database'!W18 | M30: ='Tariff Database'!X18 | N30: ='Tariff Database'!AA18 | O30: ='Tariff Database'!AB18
A31: 30 | B31: ='Tariff Database'!B20 | C31: ='Tariff Database'!C20 | D31: ='Tariff Database'!J20 | E31: ='Tariff Database'!Q20 | F31: ='Tariff Database'!P20 | G31: ='Tariff Database'!S20 | H31: ='Tariff Database'!T20 | I31: ='Tariff Database'!U20 | J31: ='Tariff Database'!R20 | K31: ='Tariff Database'!V20 | L31: ='Tariff Database'!W20 | M31: ='Tariff Database'!X20 | N31: ='Tariff Database'!AA20 | O31: ='Tariff Database'!AB20
A32: 31 | B32: ='Tariff Database'!B21 | C32: ='Tariff Database'!C21 | D32: ='Tariff Database'!J21 | E32: ='Tariff Database'!Q21 | F32: ='Tariff Database'!P21 | G32: ='Tariff Database'!S21 | H32: ='Tariff Database'!T21 | I32: ='Tariff Database'!U21 | J32: ='Tariff Database'!R21 | K32: ='Tariff Database'!V21 | L32: ='Tariff Database'!W21 | M32: ='Tariff Database'!X21 | N32: ='Tariff Database'!AA21 | O32: ='Tariff Database'!AB21
A33: 32 | B33: ='Tariff Database'!B28 | C33: ='Tariff Database'!C28 | D33: ='Tariff Database'!J28 | E33: ='Tariff Database'!Q28 | F33: ='Tariff Database'!P28 | G33: ='Tariff Database'!S28 | H33: ='Tariff Database'!T28 | I33: ='Tariff Database'!U28 | J33: ='Tariff Database'!R28 | K33: ='Tariff Database'!V28 | L33: ='Tariff Database'!W28 | M33: ='Tariff Database'!X28 | N33: ='Tariff Database'!AA28 | O33: ='Tariff Database'!AB28
A34: 33 | B34: ='Tariff Database'!B29 | C34: ='Tariff Database'!C29 | D34: ='Tariff Database'!J29 | E34: ='Tariff Database'!Q29 | F34: ='Tariff Database'!P29 | G34: ='Tariff Database'!S29 | H34: ='Tariff Database'!T29 | I34: ='Tariff Database'!U29 | J34: ='Tariff Database'!R29 | K34: ='Tariff Database'!V29 | L34: ='Tariff Database'!W29 | M34: ='Tariff Database'!X29 | N34: ='Tariff Database'!AA29 | O34: ='Tariff Database'!AB29
A35: 34 | B35: ='Tariff Database'!B31 | C35: ='Tariff Database'!C31 | D35: ='Tariff Database'!J31 | E35: ='Tariff Database'!Q31 | F35: ='Tariff Database'!P31 | G35: ='Tariff Database'!S31 | H35: ='Tariff Database'!T31 | I35: ='Tariff Database'!U31 | J35: ='Tariff Database'!R31 | K35: ='Tariff Database'!V31 | L35: ='Tariff Database'!W31 | M35: ='Tariff Database'!X31 | N35: ='Tariff Database'!AA31 | O35: ='Tariff Database'!AB31
A36: 35 | B36: ='Tariff Database'!B32 | C36: ='Tariff Database'!C32 | D36: ='Tariff Database'!J32 | E36: ='Tariff Database'!Q32 | F36: ='Tariff Database'!P32 | G36: ='Tariff Database'!S32 | H36: ='Tariff Database'!T32 | I36: ='Tariff Database'!U32 | J36: ='Tariff Database'!R32 | K36: ='Tariff Database'!V32 | L36: ='Tariff Database'!W32 | M36: ='Tariff Database'!X32 | N36: ='Tariff Database'!AA32 | O36: ='Tariff Database'!AB32
A37: 36 | B37: ='Tariff Database'!B33 | C37: ='Tariff Database'!C33 | D37: ='Tariff Database'!J33 | E37: ='Tariff Database'!Q33 | F37: ='Tariff Database'!P33 | G37: ='Tariff Database'!S33 | H37: ='Tariff Database'!T33 | I37: ='Tariff Database'!U33 | J37: ='Tariff Database'!R33 | K37: ='Tariff Database'!V33 | L37: ='Tariff Database'!W33 | M37: ='Tariff Database'!X33 | N37: ='Tariff Database'!AA33 | O37: ='Tariff Database'!AB33
A38: 37 | B38: ='Tariff Database'!B34 | C38: ='Tariff Database'!C34 | D38: ='Tariff Database'!J34 | E38: ='Tariff Database'!Q34 | F38: ='Tariff Database'!P34 | G38: ='Tariff Database'!S34 | H38: ='Tariff Database'!T34 | I38: ='Tariff Database'!U34 | J38: ='Tariff Database'!R34 | K38: ='Tariff Database'!V34 | L38: ='Tariff Database'!W34 | M38: ='Tariff Database'!X34 | N38: ='Tariff Database'!AA34 | O38: ='Tariff Database'!AB34
A39: 38 | B39: ='Tariff Database'!B35 | C39: ='Tariff Database'!C35 | D39: ='Tariff Database'!J35 | E39: ='Tariff Database'!Q35 | F39: ='Tariff Database'!P35 | G39: ='Tariff Database'!S35 | H39: ='Tariff Database'!T35 | I39: ='Tariff Database'!U35 | J39: ='Tariff Database'!R35 | K39: ='Tariff Database'!V35 | L39: ='Tariff Database'!W35 | M39: ='Tariff Database'!X35 | N39: ='Tariff Database'!AA35 | O39: ='Tariff Database'!AB35
A40: 39 | B40: ='Tariff Database'!B36 | C40: ='Tariff Database'!C36 | D40: ='Tariff Database'!J36 | E40: ='Tariff Database'!Q36 | F40: ='Tariff Database'!P36 | G40: ='Tariff Database'!S36 | H40: ='Tariff Database'!T36 | I40: ='Tariff Database'!U36 | J40: ='Tariff Database'!R36 | K40: ='Tariff Database'!V36 | L40: ='Tariff Database'!W36 | M40: ='Tariff Database'!X36 | N40: ='Tariff Database'!AA36 | O40: ='Tariff Database'!AB36
A41: 40 | B41: ='Tariff Database'!B42 | C41: ='Tariff Database'!C42 | D41: ='Tariff Database'!J42 | E41: ='Tariff Database'!Q42 | F41: ='Tariff Database'!P42 | G41: ='Tariff Database'!S42 | H41: ='Tariff Database'!T42 | I41: ='Tariff Database'!U42 | J41: ='Tariff Database'!R42 | K41: ='Tariff Database'!V42 | L41: ='Tariff Database'!W42 | M41: ='Tariff Database'!X42 | N41: ='Tariff Database'!AA42 | O41: ='Tariff Database'!AB42
A42: 41 | B42: ='Tariff Database'!B45 | C42: ='Tariff Database'!C45 | D42: ='Tariff Database'!J45 | E42: ='Tariff Database'!Q45 | F42: ='Tariff Database'!P45 | G42: ='Tariff Database'!S45 | H42: ='Tariff Database'!T45 | I42: ='Tariff Database'!U45 | J42: ='Tariff Database'!R45 | K42: ='Tariff Database'!V45 | L42: ='Tariff Database'!W45 | M42: ='Tariff Database'!X45 | N42: ='Tariff Database'!AA45 | O42: ='Tariff Database'!AB45
A43: 42 | B43: ='Tariff Database'!B46 | C43: ='Tariff Database'!C46 | D43: ='Tariff Database'!J46 | E43: ='Tariff Database'!Q46 | F43: ='Tariff Database'!P46 | G43: ='Tariff Database'!S46 | H43: ='Tariff Database'!T46 | I43: ='Tariff Database'!U46 | J43: ='Tariff Database'!R46 | K43: ='Tariff Database'!V46 | L43: ='Tariff Database'!W46 | M43: ='Tariff Database'!X46 | N43: ='Tariff Database'!AA46 | O43: ='Tariff Database'!AB46
A44: 43 | B44: ='Tariff Database'!B47 | C44: ='Tariff Database'!C47 | D44: ='Tariff Database'!J47 | E44: ='Tariff Database'!Q47 | F44: ='Tariff Database'!P47 | G44: ='Tariff Database'!S47 | H44: ='Tariff Database'!T47 | I44: ='Tariff Database'!U47 | J44: ='Tariff Database'!R47 | K44: ='Tariff Database'!V47 | L44: ='Tariff Database'!W47 | M44: ='Tariff Database'!X47 | N44: ='Tariff Database'!AA47 | O44: ='Tariff Database'!AB47
A45: 44 | B45: ='Tariff Database'!B48 | C45: ='Tariff Database'!C48 | D45: ='Tariff Database'!J48 | E45: ='Tariff Database'!Q48 | F45: ='Tariff Database'!P48 | G45: ='Tariff Database'!S48 | H45: ='Tariff Database'!T48 | I45: ='Tariff Database'!U48 | J45: ='Tariff Database'!R48 | K45: ='Tariff Database'!V48 | L45: ='Tariff Database'!W48 | M45: ='Tariff Database'!X48 | N45: ='Tariff Database'!AA48 | O45: ='Tariff Database'!AB48
A46: 45 | B46: ='Tariff Database'!B49 | C46: ='Tariff Database'!C49 | D46: ='Tariff Database'!J49 | E46: ='Tariff Database'!Q49 | F46: ='Tariff Database'!P49 | G46: ='Tariff Database'!S49 | H46: ='Tariff Database'!T49 | I46: ='Tariff Database'!U49 | J46: ='Tariff Database'!R49 | K46: ='Tariff Database'!V49 | L46: ='Tariff Database'!W49 | M46: ='Tariff Database'!X49 | N46: ='Tariff Database'!AA49 | O46: ='Tariff Database'!AB49
A47: 46 | B47: ='Tariff Database'!B50 | C47: ='Tariff Database'!C50 | D47: ='Tariff Database'!J50 | E47: ='Tariff Database'!Q50 | F47: ='Tariff Database'!P50 | G47: ='Tariff Database'!S50 | H47: ='Tariff Database'!T50 | I47: ='Tariff Database'!U50 | J47: ='Tariff Database'!R50 | K47: ='Tariff Database'!V50 | L47: ='Tariff Database'!W50 | M47: ='Tariff Database'!X50 | N47: ='Tariff Database'!AA50 | O47: ='Tariff Database'!AB50
A48: 47 | B48: ='Tariff Database'!B51 | C48: ='Tariff Database'!C51 | D48: ='Tariff Database'!J51 | E48: ='Tariff Database'!Q51 | F48: ='Tariff Database'!P51 | G48: ='Tariff Database'!S51 | H48: ='Tariff Database'!T51 | I48: ='Tariff Database'!U51 | J48: ='Tariff Database'!R51 | K48: ='Tariff Database'!V51 | L48: ='Tariff Database'!W51 | M48: ='Tariff Database'!X51 | N48: ='Tariff Database'!AA51 | O48: ='Tariff Database'!AB51
A49: 48 | B49: ='Tariff Database'!B54 | C49: ='Tariff Database'!C54 | D49: ='Tariff Database'!J54 | E49: ='Tariff Database'!Q54 | F49: ='Tariff Database'!P54 | G49: ='Tariff Database'!S54 | H49: ='Tariff Database'!T54 | I49: ='Tariff Database'!U54 | J49: ='Tariff Database'!R54 | K49: ='Tariff Database'!V54 | L49: ='Tariff Database'!W54 | M49: ='Tariff Database'!X54 | N49: ='Tariff Database'!AA54 | O49: ='Tariff Database'!AB54
A50: 49 | B50: ='Tariff Database'!B55 | C50: ='Tariff Database'!C55 | D50: ='Tariff Database'!J55 | E50: ='Tariff Database'!Q55 | F50: ='Tariff Database'!P55 | G50: ='Tariff Database'!S55 | H50: ='Tariff Database'!T55 | I50: ='Tariff Database'!U55 | J50: ='Tariff Database'!R55 | K50: ='Tariff Database'!V55 | L50: ='Tariff Database'!W55 | M50: ='Tariff Database'!X55 | N50: ='Tariff Database'!AA55 | O50: ='Tariff Database'!AB55
A51: 50 | B51: ='Tariff Database'!B56 | C51: ='Tariff Database'!C56 | D51: ='Tariff Database'!J56 | E51: ='Tariff Database'!Q56 | F51: ='Tariff Database'!P56 | G51: ='Tariff Database'!S56 | H51: ='Tariff Database'!T56 | I51: ='Tariff Database'!U56 | J51: ='Tariff Database'!R56 | K51: ='Tariff Database'!V56 | L51: ='Tariff Database'!W56 | M51: ='Tariff Database'!X56 | N51: ='Tariff Database'!AA56 | O51: ='Tariff Database'!AB56
A52: 51 | B52: ='Tariff Database'!B57 | C52: ='Tariff Database'!C57 | D52: ='Tariff Database'!J57 | E52: ='Tariff Database'!Q57 | F52: ='Tariff Database'!P57 | G52: ='Tariff Database'!S57 | H52: ='Tariff Database'!T57 | I52: ='Tariff Database'!U57 | J52: ='Tariff Database'!R57 | K52: ='Tariff Database'!V57 | L52: ='Tariff Database'!W57 | M52: ='Tariff Database'!X57 | N52: ='Tariff Database'!AA57 | O52: ='Tariff Database'!AB57
A53: 52 | B53: ='Tariff Database'!B58 | C53: ='Tariff Database'!C58 | D53: ='Tariff Database'!J58 | E53: ='Tariff Database'!Q58 | F53: ='Tariff Database'!P58 | G53: ='Tariff Database'!S58 | H53: ='Tariff Database'!T58 | I53: ='Tariff Database'!U58 | J53: ='Tariff Database'!R58 | K53: ='Tariff Database'!V58 | L53: ='Tariff Database'!W58 | M53: ='Tariff Database'!X58 | N53: ='Tariff Database'!AA58 | O53: ='Tariff Database'!AB58
A54: 53 | B54: ='Tariff Database'!B59 | C54: ='Tariff Database'!C59 | D54: ='Tariff Database'!J59 | E54: ='Tariff Database'!Q59 | F54: ='Tariff Database'!P59 | G54: ='Tariff Database'!S59 | H54: ='Tariff Database'!T59 | I54: ='Tariff Database'!U59 | J54: ='Tariff Database'!R59 | K54: ='Tariff Database'!V59 | L54: ='Tariff Database'!W59 | M54: ='Tariff Database'!X59 | N54: ='Tariff Database'!AA59 | O54: ='Tariff Database'!AB59
A55: 54 | B55: ='Tariff Database'!B60 | C55: ='Tariff Database'!C60 | D55: ='Tariff Database'!J60 | E55: ='Tariff Database'!Q60 | F55: ='Tariff Database'!P60 | G55: ='Tariff Database'!S60 | H55: ='Tariff Database'!T60 | I55: ='Tariff Database'!U60 | J55: ='Tariff Database'!R60 | K55: ='Tariff Database'!V60 | L55: ='Tariff Database'!W60 | M55: ='Tariff Database'!X60 | N55: ='Tariff Database'!AA60 | O55: ='Tariff Database'!AB60
A56: 55 | B56: ='Tariff Database'!B61 | C56: ='Tariff Database'!C61 | D56: ='Tariff Database'!J61 | E56: ='Tariff Database'!Q61 | F56: ='Tariff Database'!P61 | G56: ='Tariff Database'!S61 | H56: ='Tariff Database'!T61 | I56: ='Tariff Database'!U61 | J56: ='Tariff Database'!R61 | K56: ='Tariff Database'!V61 | L56: ='Tariff Database'!W61 | M56: ='Tariff Database'!X61 | N56: ='Tariff Database'!AA61 | O56: ='Tariff Database'!AB61
A57: 56 | B57: ='Tariff Database'!B62 | C57: ='Tariff Database'!C62 | D57: ='Tariff Database'!J62 | E57: ='Tariff Database'!Q62 | F57: ='Tariff Database'!P62 | G57: ='Tariff Database'!S62 | H57: ='Tariff Database'!T62 | I57: ='Tariff Database'!U62 | J57: ='Tariff Database'!R62 | K57: ='Tariff Database'!V62 | L57: ='Tariff Database'!W62 | M57: ='Tariff Database'!X62 | N57: ='Tariff Database'!AA62 | O57: ='Tariff Database'!AB62
A58: 57 | B58: ='Tariff Database'!B63 | C58: ='Tariff Database'!C63 | D58: ='Tariff Database'!J63 | E58: ='Tariff Database'!Q63 | F58: ='Tariff Database'!P63 | G58: ='Tariff Database'!S63 | H58: ='Tariff Database'!T63 | I58: ='Tariff Database'!U63 | J58: ='Tariff Database'!R63 | K58: ='Tariff Database'!V63 | L58: ='Tariff Database'!W63 | M58: ='Tariff Database'!X63 | N58: ='Tariff Database'!AA63 | O58: ='Tariff Database'!AB63
A59: 58 | B59: ='Tariff Database'!B65 | C59: ='Tariff Database'!C65 | D59: ='Tariff Database'!J65 | E59: ='Tariff Database'!Q65 | F59: ='Tariff Database'!P65 | G59: ='Tariff Database'!S65 | H59: ='Tariff Database'!T65 | I59: ='Tariff Database'!U65 | J59: ='Tariff Database'!R65 | K59: ='Tariff Database'!V65 | L59: ='Tariff Database'!W65 | M59: ='Tariff Database'!X65 | N59: ='Tariff Database'!AA65 | O59: ='Tariff Database'!AB65
A60: 59 | B60: ='Tariff Database'!B66 | C60: ='Tariff Database'!C66 | D60: ='Tariff Database'!J66 | E60: ='Tariff Database'!Q66 | F60: ='Tariff Database'!P66 | G60: ='Tariff Database'!S66 | H60: ='Tariff Database'!T66 | I60: ='Tariff Database'!U66 | J60: ='Tariff Database'!R66 | K60: ='Tariff Database'!V66 | L60: ='Tariff Database'!W66 | M60: ='Tariff Database'!X66 | N60: ='Tariff Database'!AA66 | O60: ='Tariff Database'!AB66
A61: 60 | B61: ='Tariff Database'!B67 | C61: ='Tariff Database'!C67 | D61: ='Tariff Database'!J67 | E61: ='Tariff Database'!Q67 | F61: ='Tariff Database'!P67 | G61: ='Tariff Database'!S67 | H61: ='Tariff Database'!T67 | I61: ='Tariff Database'!U67 | J61: ='Tariff Database'!R67 | K61: ='Tariff Database'!V67 | L61: ='Tariff Database'!W67 | M61: ='Tariff Database'!X67 | N61: ='Tariff Database'!AA67 | O61: ='Tariff Database'!AB67
A62: 61 | B62: ='Tariff Database'!B68 | C62: ='Tariff Database'!C68 | D62: ='Tariff Database'!J68 | E62: ='Tariff Database'!Q68 | F62: ='Tariff Database'!P68 | G62: ='Tariff Database'!S68 | H62: ='Tariff Database'!T68 | I62: ='Tariff Database'!U68 | J62: ='Tariff Database'!R68 | K62: ='Tariff Database'!V68 | L62: ='Tariff Database'!W68 | M62: ='Tariff Database'!X68 | N62: ='Tariff Database'!AA68 | O62: ='Tariff Database'!AB68
A63: 62 | B63: ='Tariff Database'!B69 | C63: ='Tariff Database'!C69 | D63: ='Tariff Database'!J69 | E63: ='Tariff Database'!Q69 | F63: ='Tariff Database'!P69 | G63: ='Tariff Database'!S69 | H63: ='Tariff Database'!T69 | I63: ='Tariff Database'!U69 | J63: ='Tariff Database'!R69 | K63: ='Tariff Database'!V69 | L63: ='Tariff Database'!W69 | M63: ='Tariff Database'!X69 | N63: ='Tariff Database'!AA69 | O63: ='Tariff Database'!AB69
A64: 63 | B64: ='Tariff Database'!B70 | C64: ='Tariff Database'!C70 | D64: ='Tariff Database'!J70 | E64: ='Tariff Database'!Q70 | F64: ='Tariff Database'!P70 | G64: ='Tariff Database'!S70 | H64: ='Tariff Database'!T70 | I64: ='Tariff Database'!U70 | J64: ='Tariff Database'!R70 | K64: ='Tariff Database'!V70 | L64: ='Tariff Database'!W70 | M64: ='Tariff Database'!X70 | N64: ='Tariff Database'!AA70 | O64: ='Tariff Database'!AB70
A65: 64 | B65: ='Tariff Database'!B71 | C65: ='Tariff Database'!C71 | D65: ='Tariff Database'!J71 | E65: ='Tariff Database'!Q71 | F65: ='Tariff Database'!P71 | G65: ='Tariff Database'!S71 | H65: ='Tariff Database'!T71 | I65: ='Tariff Database'!U71 | J65: ='Tariff Database'!R71 | K65: ='Tariff Database'!V71 | L65: ='Tariff Database'!W71 | M65: ='Tariff Database'!X71 | N65: ='Tariff Database'!AA71 | O65: ='Tariff Database'!AB71
A66: 65 | B66: ='Tariff Database'!B72 | C66: ='Tariff Database'!C72 | D66: ='Tariff Database'!J72 | E66: ='Tariff Database'!Q72 | F66: ='Tariff Database'!P72 | G66: ='Tariff Database'!S72 | H66: ='Tariff Database'!T72 | I66: ='Tariff Database'!U72 | J66: ='Tariff Database'!R72 | K66: ='Tariff Database'!V72 | L66: ='Tariff Database'!W72 | M66: ='Tariff Database'!X72 | N66: ='Tariff Database'!AA72 | O66: ='Tariff Database'!AB72
A67: 66 | B67: ='Tariff Database'!B73 | C67: ='Tariff Database'!C73 | D67: ='Tariff Database'!J73 | E67: ='Tariff Database'!Q73 | F67: ='Tariff Database'!P73 | G67: ='Tariff Database'!S73 | H67: ='Tariff Database'!T73 | I67: ='Tariff Database'!U73 | J67: ='Tariff Database'!R73 | K67: ='Tariff Database'!V73 | L67: ='Tariff Database'!W73 | M67: ='Tariff Database'!X73 | N67: ='Tariff Database'!AA73 | O67: ='Tariff Database'!AB73
A68: 67 | B68: ='Tariff Database'!B74 | C68: ='Tariff Database'!C74 | D68: ='Tariff Database'!J74 | E68: ='Tariff Database'!Q74 | F68: ='Tariff Database'!P74 | G68: ='Tariff Database'!S74 | H68: ='Tariff Database'!T74 | I68: ='Tariff Database'!U74 | J68: ='Tariff Database'!R74 | K68: ='Tariff Database'!V74 | L68: ='Tariff Database'!W74 | M68: ='Tariff Database'!X74 | N68: ='Tariff Database'!AA74 | O68: ='Tariff Database'!AB74
A69: 68 | B69: ='Tariff Database'!B4 | C69: ='Tariff Database'!C4 | D69: ='Tariff Database'!J4 | E69: ='Tariff Database'!Q4 | F69: ='Tariff Database'!P4 | G69: ='Tariff Database'!S4 | H69: ='Tariff Database'!T4 | I69: ='Tariff Database'!U4 | J69: ='Tariff Database'!R4 | K69: ='Tariff Database'!V4 | L69: ='Tariff Database'!W4 | M69: ='Tariff Database'!X4 | N69: ='Tariff Database'!AA4 | O69: ='Tariff Database'!AB4
A70: 69 | B70: ='Tariff Database'!B7 | C70: ='Tariff Database'!C7 | D70: ='Tariff Database'!J7 | E70: ='Tariff Database'!Q7 | F70: ='Tariff Database'!P7 | G70: ='Tariff Database'!S7 | H70: ='Tariff Database'!T7 | I70: ='Tariff Database'!U7 | J70: ='Tariff Database'!R7 | K70: ='Tariff Database'!V7 | L70: ='Tariff Database'!W7 | M70: ='Tariff Database'!X7 | N70: ='Tariff Database'!AA7 | O70: ='Tariff Database'!AB7
A71: 70 | B71: ='Tariff Database'!B8 | C71: ='Tariff Database'!C8 | D71: ='Tariff Database'!J8 | E71: ='Tariff Database'!Q8 | F71: ='Tariff Database'!P8 | G71: ='Tariff Database'!S8 | H71: ='Tariff Database'!T8 | I71: ='Tariff Database'!U8 | J71: ='Tariff Database'!R8 | K71: ='Tariff Database'!V8 | L71: ='Tariff Database'!W8 | M71: ='Tariff Database'!X8 | N71: ='Tariff Database'!AA8 | O71: ='Tariff Database'!AB8
A72: 71 | B72: ='Tariff Database'!B26 | C72: ='Tariff Database'!C26 | D72: ='Tariff Database'!J26 | E72: ='Tariff Database'!Q26 | F72: ='Tariff Database'!P26 | G72: ='Tariff Database'!S26 | H72: ='Tariff Database'!T26 | I72: ='Tariff Database'!U26 | J72: ='Tariff Database'!R26 | K72: ='Tariff Database'!V26 | L72: ='Tariff Database'!W26 | M72: ='Tariff Database'!X26 | N72: ='Tariff Database'!AA26 | O72: ='Tariff Database'!AB26
A73: 72 | B73: ='Tariff Database'!B27 | C73: ='Tariff Database'!C27 | D73: ='Tariff Database'!J27 | E73: ='Tariff Database'!Q27 | F73: ='Tariff Database'!P27 | G73: ='Tariff Database'!S27 | H73: ='Tariff Database'!T27 | I73: ='Tariff Database'!U27 | J73: ='Tariff Database'!R27 | K73: ='Tariff Database'!V27 | L73: ='Tariff Database'!W27 | M73: ='Tariff Database'!X27 | N73: ='Tariff Database'!AA27 | O73: ='Tariff Database'!AB27
A74: 73 | B74: ='Tariff Database'!B75 | C74: ='Tariff Database'!C75 | D74: ='Tariff Database'!J75 | E74: ='Tariff Database'!Q75 | F74: ='Tariff Database'!P75 | G74: ='Tariff Database'!S75 | H74: ='Tariff Database'!T75 | I74: ='Tariff Database'!U75 | J74: ='Tariff Database'!R75 | K74: ='Tariff Database'!V75 | L74: ='Tariff Database'!W75 | M74: ='Tariff Database'!X75 | N74: ='Tariff Database'!AA75 | O74: ='Tariff Database'!AB75
A75: 74 | B75: ='Tariff Database'!B76 | C75: ='Tariff Database'!C76 | D75: ='Tariff Database'!J76 | E75: ='Tariff Database'!Q76 | F75: ='Tariff Database'!P76 | G75: ='Tariff Database'!S76 | H75: ='Tariff Database'!T76 | I75: ='Tariff Database'!U76 | J75: ='Tariff Database'!R76 | K75: ='Tariff Database'!V76 | L75: ='Tariff Database'!W76 | M75: ='Tariff Database'!X76 | N75: ='Tariff Database'!AA76 | O75: ='Tariff Database'!AB76
A76: 75 | B76: ='Tariff Database'!B77 | C76: ='Tariff Database'!C77 | D76: ='Tariff Database'!J77 | E76: ='Tariff Database'!Q77 | F76: ='Tariff Database'!P77 | G76: ='Tariff Database'!S77 | H76: ='Tariff Database'!T77 | I76: ='Tariff Database'!U77 | J76: ='Tariff Database'!R77 | K76: ='Tariff Database'!V77 | L76: ='Tariff Database'!W77 | M76: ='Tariff Database'!X77 | N76: ='Tariff Database'!AA77 | O76: ='Tariff Database'!AB77
A77: 76 | B77: ='Tariff Database'!B78 | C77: ='Tariff Database'!C78 | D77: ='Tariff Database'!J78 | E77: ='Tariff Database'!Q78 | F77: ='Tariff Database'!P78 | G77: ='Tariff Database'!S78 | H77: ='Tariff Database'!T78 | I77: ='Tariff Database'!U78 | J77: ='Tariff Database'!R78 | K77: ='Tariff Database'!V78 | L77: ='Tariff Database'!W78 | M77: ='Tariff Database'!X78 | N77: ='Tariff Database'!AA78 | O77: ='Tariff Database'!AB78
A78: 77 | B78: ='Tariff Database'!B79 | C78: ='Tariff Database'!C79 | D78: ='Tariff Database'!J79 | E78: ='Tariff Database'!Q79 | F78: ='Tariff Database'!P79 | G78: ='Tariff Database'!S79 | H78: ='Tariff Database'!T79 | I78: ='Tariff Database'!U79 | J78: ='Tariff Database'!R79 | K78: ='Tariff Database'!V79 | L78: ='Tariff Database'!W79 | M78: ='Tariff Database'!X79 | N78: ='Tariff Database'!AA79 | O78: ='Tariff Database'!AB79
A79: 78 | B79: ='Tariff Database'!B80 | C79: ='Tariff Database'!C80 | D79: ='Tariff Database'!J80 | E79: ='Tariff Database'!Q80 | F79: ='Tariff Database'!P80 | G79: ='Tariff Database'!S80 | H79: ='Tariff Database'!T80 | I79: ='Tariff Database'!U80 | J79: ='Tariff Database'!R80 | K79: ='Tariff Database'!V80 | L79: ='Tariff Database'!W80 | M79: ='Tariff Database'!X80 | N79: ='Tariff Database'!AA80 | O79: ='Tariff Database'!AB80
A80: 79 | B80: ='Tariff Database'!B81 | C80: ='Tariff Database'!C81 | D80: ='Tariff Database'!J81 | E80: ='Tariff Database'!Q81 | F80: ='Tariff Database'!P81 | G80: ='Tariff Database'!S81 | H80: ='Tariff Database'!T81 | I80: ='Tariff Database'!U81 | J80: ='Tariff Database'!R81 | K80: ='Tariff Database'!V81 | L80: ='Tariff Database'!W81 | M80: ='Tariff Database'!X81 | N80: ='Tariff Database'!AA81 | O80: ='Tariff Database'!AB81
A81: 80 | B81: ='Tariff Database'!B82 | C81: ='Tariff Database'!C82 | D81: ='Tariff Database'!J82 | E81: ='Tariff Database'!Q82 | F81: ='Tariff Database'!P82 | G81: ='Tariff Database'!S82 | H81: ='Tariff Database'!T82 | I81: ='Tariff Database'!U82 | J81: ='Tariff Database'!R82 | K81: ='Tariff Database'!V82 | L81: ='Tariff Database'!W82 | M81: ='Tariff Database'!X82 | N81: ='Tariff Database'!AA82 | O81: ='Tariff Database'!AB82
A82: 81 | B82: ='Tariff Database'!B83 | C82: ='Tariff Database'!C83 | D82: ='Tariff Database'!J83 | E82: ='Tariff Database'!Q83 | F82: ='Tariff Database'!P83 | G82: ='Tariff Database'!S83 | H82: ='Tariff Database'!T83 | I82: ='Tariff Database'!U83 | J82: ='Tariff Database'!R83 | K82: ='Tariff Database'!V83 | L82: ='Tariff Database'!W83 | M82: ='Tariff Database'!X83 | N82: ='Tariff Database'!AA83 | O82: ='Tariff Database'!AB83
A83: 82 | B83: ='Tariff Database'!B84 | C83: ='Tariff Database'!C84 | D83: ='Tariff Database'!J84 | E83: ='Tariff Database'!Q84 | F83: ='Tariff Database'!P84 | G83: ='Tariff Database'!S84 | H83: ='Tariff Database'!T84 | I83: ='Tariff Database'!U84 | J83: ='Tariff Database'!R84 | K83: ='Tariff Database'!V84 | L83: ='Tariff Database'!W84 | M83: ='Tariff Database'!X84 | N83: ='Tariff Database'!AA84 | O83: ='Tariff Database'!AB84
A84: 83 | B84: ='Tariff Database'!B85 | C84: ='Tariff Database'!C85 | D84: ='Tariff Database'!J85 | E84: ='Tariff Database'!Q85 | F84: ='Tariff Database'!P85 | G84: ='Tariff Database'!S85 | H84: ='Tariff Database'!T85 | I84: ='Tariff Database'!U85 | J84: ='Tariff Database'!R85 | K84: ='Tariff Database'!V85 | L84: ='Tariff Database'!W85 | M84: ='Tariff Database'!X85 | N84: ='Tariff Database'!AA85 | O84: ='Tariff Database'!AB85
A85: 84 | B85: ='Tariff Database'!B86 | C85: ='Tariff Database'!C86 | D85: ='Tariff Database'!J86 | E85: ='Tariff Database'!Q86 | F85: ='Tariff Database'!P86 | G85: ='Tariff Database'!S86 | H85: ='Tariff Database'!T86 | I85: ='Tariff Database'!U86 | J85: ='Tariff Database'!R86 | K85: ='Tariff Database'!V86 | L85: ='Tariff Database'!W86 | M85: ='Tariff Database'!X86 | N85: ='Tariff Database'!AA86 | O85: ='Tariff Database'!AB86
... A89: 88 | B89: ='Tariff Database'!B90 | C89: ='Tariff Database'!C90 | D89: ='Tariff Database'!J90 | E89: ='Tariff Database'!Q90 | F89: ='Tariff Database'!P90 | G89: ='Tariff Database'!S90 | H89: ='Tariff Database'!T90 | I89: ='Tariff Database'!U90 | J89: ='Tariff Database'!R90 | K89: ='Tariff Database'!V90 | L89: ='Tariff Database'!W90 | M89: ='Tariff Database'!X90 | N89: ='Tariff Database'!AA90 | O89: ='Tariff Database'!AB90

Sheet Document Citations
A1: Utility | B1: Source Document | C1: URL | D1: Page/Table Reference | E1: Docket Number
A2: Public Service Company of Oklahoma (PSO) | B2: PSO Large Commercial and Industrial Tariff, 9th Revised Sheet No. 20 | C2: https://www.psoklahoma.com/lib/docs/ratesandtariffs/Oklahoma/PSOLargeCommercialandIndustrialFeb2025.pdf | D2: Sheet No. 20-3 (Minimum Monthly Demand) | E2: PUD 2023-000086 (Order 746624)
A3: Oklahoma Gas & Electric (OG&E) | B3: OG&E Oklahoma Rate Tariff, Schedule 19.00 OCT-1 | C3: https://www.oge.com/documents/d/portal/19-00-oct-1-stamped-approved | D3: Schedule 19.00, 1st Revised Sheet | E3: PUD 2023-000087
A4: SWEPCO (AEP) | B4: SWEPCO Texas Tariff Manual | C4: https://www.swepco.com/lib/docs/ratesandtariffs/Texas/TexasRatesChargesandFees.pdf | D4: ES-LL Section | E4: PUCT Filing Oct 2025
A5: ERCOT Market (via REP) | B5: ERCOT Nodal Protocols, Section 7 (Transmission) | C5: https://www.ercot.com/mktrules/nprotocols | D5: Protocol Section 7.7 (4CP Calculation) | E5: PUCT Project 52376
A6: Oncor Electric Delivery | B6: Oncor Tariff for Retail Delivery Service | C6: https://www.oncor.com/content/dam/oncorwww/documents/tariff/OnDTTariff.pdf | D6: Schedule 1700, Large Industrial | E6: PUCT Docket 54870
A7: CenterPoint Energy Houston | B7: CenterPoint Energy Houston Electric Tariff | C7: https://www.centerpointenergy.com/en-us/corp/pages/rates-and-tariffs-electric.aspx | D7: Schedule GSLV-630 | E7: PUCT Docket 55678
A8: CPS Energy (San Antonio) | B8: CPS Energy Commercial Rate Schedules | C8: https://www.cpsenergy.com/en/my-home/rates/commercial-rates.html | D8: Rate E LCI | E8: CPS Board
A9: Austin Energy | B9: Austin Energy Rate Schedule | C9: https://austinenergy.com/ae/rates/commercial-rates | D9: Rate P4 | E9: Austin City Council
A10: Georgia Power | B10: Georgia Power PLL-11 Rate Schedule | C10: https://www.georgiapower.com/content/dam/georgia-power/pdfs/business-pdfs/rates-schedules/small-business/PLL-11.pdf | D10: PLL-11, Page 1 (Demand Charge) | E10: GA PSC Docket 44280
A11: Duke Energy Carolinas | B11: Duke Energy Carolinas Schedule LGS | C11: https://www.duke-energy.com/home/billing/rates | D11: Schedule LGS, Effective 9/1/2024 | E11: NC Docket E-7, Sub 1276
A12: Duke Energy Florida | B12: Duke Energy Florida LLC-1 Filing, Document 09146-2025 | C12: https://www.floridapsc.com/pscfiles/library/filings/2025/09146-2025/09146-2025.pdf | D12: Docket 20250113-EI, Filed 9/5/2025 | E12: FL PSC Docket 20250113-EI
... A89: Duke Energy Ohio | B89: Duke Energy Ohio Rate DP | C89: https://www.duke-energy.com/rates/ohio | D89: Schedule DP | E89: OH PUCO

Sheet Scoring Methodology
A1: PROTECTION SCORING METHODOLOGY
A3: Category | B3: Criteria | C3: Points
A4: Minimum Demand (Ratchet %) | B4: >= 90% of contract demand | C4: +3
A5: Minimum Demand (Ratchet %) | B5: 80-89% of contract demand | C5: +2
A6: Minimum Demand (Ratchet %) | B6: 60-79% of contract demand | C6: +1
A7: Contract Term | B7: >= 15 years | C7: +3
A8: Contract Term | B8: 10-14 years | C8: +2
A9: Contract Term | B9: 5-9 years | C9: +1
A10: CIAC Required | B10: Yes | C10: +2
A11: Take-or-Pay | B11: Yes | C11: +2
A12: Exit Fee | B12: Yes | C12: +2
A13: Demand Ratchet | B13: Yes | C13: +1
A14: Credit Requirements | B14: Yes | C14: +1
... A17: Minimum Load Threshold | B17: >= 50 MW | C17: +1
A19: Maximum Possible Score | C19: 19
A21: SCORE THRESHOLDS
A22: High Protection | B22: >= 14 points | C22: Strong ratepayer protections; challenging for data centers
A23: Mid Protection | B23: 8-13 points | C23: Moderate protections; negotiable terms
A24: Low Protection | B24: < 8 points | C24: Minimal protections; favorable for data centers
A26: INTERPRETATION
A27: HIGH score | B27: =More difficult provisions for data centers
A28: LOW score | B28: =More favorable provisions for data centers
A30: FORMULA USED IN TARIFF DATABASE:
A31: =IF(Ratchet%>=90,3,IF(Ratchet%>=80,2,IF(Ratchet%>=60,1,0))) | C31: Ratchet % component
A32: +IF(Contract>=15,3,IF(Contract>=10,2,IF(Contract>=5,1,0))) | C32: Contract term component
A33: +IF(CIAC="Yes",2,0)+IF(Take-or-Pay="Yes",2,0)+IF(Exit Fee="Yes",2,0) | C33: Financial security
A34: +IF(Ratchet="Yes",1,0)+IF(Credit="Yes",1,0)+IF(DC="Yes",2,0)+IF(Collateral="Yes",1,0) | C34: Other provisions
A35: +IF(Min Load>=50,1,0) | C35: Load threshold

Sheet QA-QC Summary
A1: LARGE LOAD TARIFF DATABASE - QA/QC SUMMARY
A2: Generated: January 2026
A4: DATABASE STATISTICS
A5: Total Utilities | B5: 72
A6: States Covered | B6: 45
A8: BLENDED RATE METHODOLOGY
A9: Data Center Size | B9: 600 MW
A10: Load Factor | B10: 80%
A11: Average Load | B11: 480 MW
A12: Monthly Consumption | B12: 350,400,000 kWh
A13: Peak Hours (40%) | B13: 140,160,000 kWh
A14: Off-Peak Hours (60%) | B14: 210,240,000 kWh
A15: Billing Demand | B15: 600,000 kW
A17: FORMULA
A18: Blended Rate | B18: =(@Demand Cost +@ Energy Cost +@ Fixed) /@ Total kWh
A19: Demand Cost
A20: Energy Cost | B20: =(@Peak Energy +@ Fuel) *@ Peak kWh + (@Off-@Peak +@ Fuel) *@ Off-@Peak kWh
A22: QA/QC CORRECTIONS APPLIED
A23: We Energies | B23: Demand charge $305→$21.62/kW | C23: Decimal error
A24: ERCOT | B24: Renamed to "ERCOT Market (via REP)" | C24: Not a retailer
A25: Oncor/CenterPoint | B25: Added REP energy charges | C25: TDU-only
A26: OK/TX/GA utilities | B26: Added fuel adjustment riders | C26: Missing fuel costs
A27: Black Hills | B27: Added minimum load requirements | C27: Missing thresholds
A28: Pepco/PECO | B28: Added missing major PJM utilities | C28: Coverage gap
A29: FirstEnergy | B29: Added OH/PA/NJ operating companies | C29: Coverage gap
A31: DATA SOURCES
A32: E3 Study | B32: "Tailored for Scale" (2024)
A33: State PUC Filings | B33: Rate cases, tariff filings
A34: Utility Tariffs | B34: Published rate schedules
A35: ISO/RTO Documents | B35: OATT, market rules
A36: QA/QC Audit - Feb 2026 | B36: Applied 19 corrections | C36: 2026-02-01 11:48
A37: Critical Fix | B37: FPL IGC charge added ($28.07/kW) | C37: $191M/yr variance corrected
A38: Status Updates | B38: FPL→Active, Duke FL→Suspended | C38: Regulatory latency correction
A39: Tariff Rename | B39: AEP Ohio GS-4→DCT | C39: Per PUCO July 2025 order
A40: Rate Correction | B40: We Energies $21.62→$22.59/kW | C40: Per current tariff book
